{
  "id": "J83g6ABM9WkKAs8jRCiccd",
  "songId": "Wdsud58RuDyYmrpW4c1EQQ",
  "title": "9.2",
  "subtitle": "",
  "startAt": 0,
  "endAt": 0,
  "keys": 4,
  "difficulty": 9,
  "length": 217.536,
  "noteCount": 1070,
  "bpm": 0,
  "svCount": 0,
  "visualizerName": "",
  "visibility": "public",
  "isImported": false,
  "importedFrom": "",
  "importRef": "",
  "importIsOriginal": false,
  "mapping": "{\"version\":1,\"title\":\"\",\"startAt\":null,\"endAt\":null,\"keys\":4,\"difficulty\":9,\"length\":217.536,\"noteCount\":1070,\"visualizerName\":\"\",\"clonedFrom\":\"\",\"mappings\":[{\"t\":1.673,\"k\":\"jf\"},{\"t\":1.883,\"k\":\"jf\"},{\"t\":2.085,\"k\":\"k\"},{\"t\":2.182,\"k\":\"d\"},{\"t\":2.281,\"k\":\"j\"},{\"t\":2.484,\"k\":\"fj\"},{\"t\":2.637,\"k\":\"fj\"},{\"t\":2.796,\"k\":\"k\"},{\"t\":2.883,\"k\":\"d\"},{\"t\":2.982,\"k\":\"j\"},{\"t\":3.117,\"k\":\"f\"},{\"t\":3.168,\"k\":\"k\"},{\"t\":3.348,\"k\":\"d\"},{\"t\":3.395,\"k\":\"j\"},{\"t\":3.71,\"k\":\"k\",\"h\":{\"k\":4.378849895572662}},{\"t\":4.137,\"k\":\"f\"},{\"t\":4.452,\"k\":\"j\"},{\"t\":4.613,\"k\":\"d\"},{\"t\":4.762,\"k\":\"k\"},{\"t\":4.96,\"k\":\"f\"},{\"t\":5.104,\"k\":\"j\"},{\"t\":5.286,\"k\":\"d\"},{\"t\":5.463,\"k\":\"k\"},{\"t\":5.714,\"k\":\"f\"},{\"t\":5.899,\"k\":\"j\"},{\"t\":6.124,\"k\":\"d\"},{\"t\":6.312,\"k\":\"k\"},{\"t\":6.489,\"k\":\"f\"},{\"t\":6.648,\"k\":\"j\"},{\"t\":6.827,\"k\":\"d\"},{\"t\":6.987,\"k\":\"k\"},{\"t\":7.167,\"k\":\"f\"},{\"t\":7.327,\"k\":\"j\"},{\"t\":7.476,\"k\":\"f\"},{\"t\":7.677,\"k\":\"k\"},{\"t\":7.837,\"k\":\"d\"},{\"t\":7.999,\"k\":\"j\"},{\"t\":8.158,\"k\":\"f\"},{\"t\":8.335,\"k\":\"k\"},{\"t\":8.538,\"k\":\"d\"},{\"t\":8.762,\"k\":\"j\"},{\"t\":8.896,\"k\":\"f\"},{\"t\":9.099,\"k\":\"k\"},{\"t\":9.232,\"k\":\"d\"},{\"t\":9.358,\"k\":\"j\"},{\"t\":9.635,\"k\":\"j\"},{\"t\":9.713,\"k\":\"j\"},{\"t\":9.851,\"k\":\"f\"},{\"t\":9.975,\"k\":\"k\"},{\"t\":10.126,\"k\":\"d\"},{\"t\":10.274,\"k\":\"j\"},{\"t\":10.44,\"k\":\"f\"},{\"t\":10.588,\"k\":\"k\"},{\"t\":10.891,\"k\":\"d\"},{\"t\":10.989,\"k\":\"j\"},{\"t\":11.209,\"k\":\"f\"},{\"t\":11.342,\"k\":\"k\"},{\"t\":11.543,\"k\":\"d\"},{\"t\":11.642,\"k\":\"j\"},{\"t\":11.906,\"k\":\"f\"},{\"t\":12.108,\"k\":\"k\"},{\"t\":12.288,\"k\":\"d\"},{\"t\":12.424,\"k\":\"j\"},{\"t\":12.604,\"k\":\"f\"},{\"t\":12.789,\"k\":\"k\"},{\"t\":12.974,\"k\":\"d\"},{\"t\":13.141,\"k\":\"j\"},{\"t\":13.309,\"k\":\"f\"},{\"t\":13.453,\"k\":\"k\"},{\"t\":13.637,\"k\":\"d\"},{\"t\":13.902,\"k\":\"d\"},{\"t\":14.016,\"k\":\"f\"},{\"t\":14.177,\"k\":\"j\"},{\"t\":14.363,\"k\":\"k\"},{\"t\":14.528,\"k\":\"d\"},{\"t\":14.689,\"k\":\"j\"},{\"t\":14.816,\"k\":\"f\"},{\"t\":15.497,\"k\":\"df\"},{\"t\":15.681,\"k\":\"jk\"},{\"t\":15.846,\"k\":\"fd\"},{\"t\":16.147,\"k\":\"jf\"},{\"t\":16.391,\"k\":\"k\"},{\"t\":16.545,\"k\":\"d\"},{\"t\":16.682,\"k\":\"j\"},{\"t\":16.81,\"k\":\"f\"},{\"t\":16.945,\"k\":\"k\"},{\"t\":17.096,\"k\":\"d\"},{\"t\":17.232,\"k\":\"j\"},{\"t\":17.393,\"k\":\"f\"},{\"t\":17.527,\"k\":\"k\"},{\"t\":17.691,\"k\":\"d\"},{\"t\":17.839,\"k\":\"j\"},{\"t\":18.001,\"k\":\"f\"},{\"t\":18.148,\"k\":\"k\"},{\"t\":18.307,\"k\":\"d\"},{\"t\":18.481,\"k\":\"j\"},{\"t\":19.104,\"k\":\"j\"},{\"t\":19.229,\"k\":\"f\"},{\"t\":19.339,\"k\":\"k\"},{\"t\":19.504,\"k\":\"d\"},{\"t\":19.653,\"k\":\"j\"},{\"t\":19.847,\"k\":\"f\"},{\"t\":19.998,\"k\":\"k\"},{\"t\":20.189,\"k\":\"d\"},{\"t\":20.383,\"k\":\"f\"},{\"t\":20.552,\"k\":\"j\"},{\"t\":20.757,\"k\":\"k\"},{\"t\":20.94,\"k\":\"j\"},{\"t\":21.109,\"k\":\"f\"},{\"t\":21.275,\"k\":\"d\"},{\"t\":21.441,\"k\":\"j\"},{\"t\":21.688,\"k\":\"f\"},{\"t\":21.84,\"k\":\"k\"},{\"t\":22.025,\"k\":\"d\"},{\"t\":22.158,\"k\":\"j\"},{\"t\":22.349,\"k\":\"f\"},{\"t\":22.509,\"k\":\"k\"},{\"t\":22.658,\"k\":\"d\"},{\"t\":22.837,\"k\":\"j\"},{\"t\":23.024,\"k\":\"f\"},{\"t\":23.178,\"k\":\"k\"},{\"t\":23.36,\"k\":\"d\"},{\"t\":23.495,\"k\":\"j\"},{\"t\":23.681,\"k\":\"f\"},{\"t\":23.862,\"k\":\"k\"},{\"t\":24.015,\"k\":\"d\"},{\"t\":24.181,\"k\":\"j\"},{\"t\":24.351,\"k\":\"f\"},{\"t\":24.53,\"k\":\"k\"},{\"t\":24.704,\"k\":\"d\"},{\"t\":24.862,\"k\":\"j\"},{\"t\":25.061,\"k\":\"f\"},{\"t\":25.249,\"k\":\"k\"},{\"t\":25.424,\"k\":\"d\"},{\"t\":25.579,\"k\":\"j\"},{\"t\":25.81,\"k\":\"f\"},{\"t\":25.996,\"k\":\"k\"},{\"t\":26.179,\"k\":\"d\"},{\"t\":26.33,\"k\":\"j\"},{\"t\":26.512,\"k\":\"f\"},{\"t\":26.652,\"k\":\"j\"},{\"t\":26.788,\"k\":\"f\"},{\"t\":26.946,\"k\":\"j\"},{\"t\":27.065,\"k\":\"f\"},{\"t\":27.199,\"k\":\"j\"},{\"t\":27.302,\"k\":\"d\"},{\"t\":27.485,\"k\":\"fk\"},{\"t\":27.642,\"k\":\"j\"},{\"t\":27.783,\"k\":\"f\"},{\"t\":27.915,\"k\":\"d\"},{\"t\":28.111,\"k\":\"j\"},{\"t\":28.451,\"k\":\"jf\"},{\"t\":28.731,\"k\":\"kd\"},{\"t\":29.039,\"k\":\"j\"},{\"t\":29.165,\"k\":\"f\"},{\"t\":29.283,\"k\":\"k\"},{\"t\":29.383,\"k\":\"d\"},{\"t\":29.592,\"k\":\"k\",\"h\":{\"k\":30.40428804577637}},{\"t\":29.781,\"k\":\"f\"},{\"t\":29.943,\"k\":\"j\"},{\"t\":30.116,\"k\":\"d\"},{\"t\":30.837,\"k\":\"j\"},{\"t\":31.004,\"k\":\"fk\"},{\"t\":31.202,\"k\":\"d\"},{\"t\":31.312,\"k\":\"j\"},{\"t\":31.453,\"k\":\"f\"},{\"t\":31.554,\"k\":\"k\"},{\"t\":31.983,\"k\":\"d\"},{\"t\":32.149,\"k\":\"j\"},{\"t\":32.287,\"k\":\"f\"},{\"t\":32.554,\"k\":\"d\",\"h\":{\"d\":33.66918103051758}},{\"t\":32.82,\"k\":\"f\"},{\"t\":33.069,\"k\":\"j\"},{\"t\":33.774,\"k\":\"j\"},{\"t\":33.914,\"k\":\"f\"},{\"t\":34.008,\"k\":\"j\"},{\"t\":34.141,\"k\":\"d\"},{\"t\":34.39,\"k\":\"k\"},{\"t\":34.656,\"k\":\"fj\"},{\"t\":34.99,\"k\":\"k\"},{\"t\":35.143,\"k\":\"d\"},{\"t\":35.264,\"k\":\"j\"},{\"t\":35.422,\"k\":\"f\"},{\"t\":35.54,\"k\":\"k\"},{\"t\":35.848,\"k\":\"d\"},{\"t\":36.141,\"k\":\"kj\"},{\"t\":36.21,\"k\":\"df\"},{\"t\":36.939,\"k\":\"j\"},{\"t\":37.107,\"k\":\"f\"},{\"t\":37.192,\"k\":\"j\"},{\"t\":37.326,\"k\":\"d\"},{\"t\":37.425,\"k\":\"k\"},{\"t\":37.609,\"k\":\"fj\"},{\"t\":37.96,\"k\":\"k\"},{\"t\":38.093,\"k\":\"d\"},{\"t\":38.226,\"k\":\"j\"},{\"t\":38.415,\"k\":\"f\"},{\"t\":38.559,\"k\":\"k\"},{\"t\":38.787,\"k\":\"f\"},{\"t\":38.973,\"k\":\"j\"},{\"t\":39.11,\"k\":\"d\"},{\"t\":39.895,\"k\":\"d\"},{\"t\":40.097,\"k\":\"d\"},{\"t\":40.255,\"k\":\"f\"},{\"t\":40.379,\"k\":\"j\"},{\"t\":40.682,\"k\":\"k\"},{\"t\":40.863,\"k\":\"k\"},{\"t\":41.113,\"k\":\"j\"},{\"t\":41.247,\"k\":\"f\"},{\"t\":41.381,\"k\":\"d\"},{\"t\":41.745,\"k\":\"d\"},{\"t\":41.979,\"k\":\"d\"},{\"t\":42.134,\"k\":\"jf\"},{\"t\":42.349,\"k\":\"k\"},{\"t\":42.548,\"k\":\"j\"},{\"t\":42.914,\"k\":\"j\"},{\"t\":43.079,\"k\":\"j\"},{\"t\":43.247,\"k\":\"f\"},{\"t\":43.398,\"k\":\"d\"},{\"t\":43.747,\"k\":\"f\"},{\"t\":43.957,\"k\":\"f\"},{\"t\":44.116,\"k\":\"f\"},{\"t\":44.218,\"k\":\"j\"},{\"t\":44.384,\"k\":\"j\"},{\"t\":44.517,\"k\":\"k\"},{\"t\":44.719,\"k\":\"d\"},{\"t\":44.853,\"k\":\"j\"},{\"t\":45.167,\"k\":\"dk\"},{\"t\":45.366,\"k\":\"j\"},{\"t\":45.419,\"k\":\"f\"},{\"t\":45.882,\"k\":\"k\"},{\"t\":46.052,\"k\":\"k\"},{\"t\":46.232,\"k\":\"j\"},{\"t\":46.315,\"k\":\"f\"},{\"t\":46.446,\"k\":\"d\"},{\"t\":46.733,\"k\":\"d\"},{\"t\":46.916,\"k\":\"d\"},{\"t\":47.049,\"k\":\"f\"},{\"t\":47.182,\"k\":\"j\"},{\"t\":47.336,\"k\":\"k\"},{\"t\":47.571,\"k\":\"j\"},{\"t\":47.738,\"k\":\"j\"},{\"t\":47.887,\"k\":\"f\"},{\"t\":48.03,\"k\":\"d\"},{\"t\":48.4,\"k\":\"f\"},{\"t\":48.604,\"k\":\"f\"},{\"t\":48.781,\"k\":\"f\"},{\"t\":48.904,\"k\":\"j\"},{\"t\":49.087,\"k\":\"k\"},{\"t\":49.404,\"k\":\"j\"},{\"t\":49.557,\"k\":\"j\"},{\"t\":49.671,\"k\":\"f\"},{\"t\":49.821,\"k\":\"d\"},{\"t\":50.272,\"k\":\"kd\"},{\"t\":50.471,\"k\":\"j\"},{\"t\":50.552,\"k\":\"f\"},{\"t\":50.687,\"k\":\"k\"},{\"t\":50.808,\"k\":\"d\"},{\"t\":50.891,\"k\":\"j\"},{\"t\":51.107,\"k\":\"fj\",\"h\":{\"f\":51.44239910108948,\"j\":51.49239905340576}},{\"t\":51.446,\"k\":\"dk\"},{\"t\":51.811,\"k\":\"k\"},{\"t\":52.008,\"k\":\"f\"},{\"t\":52.096,\"k\":\"j\"},{\"t\":52.274,\"k\":\"d\"},{\"t\":52.425,\"k\":\"k\"},{\"t\":52.741,\"k\":\"k\"},{\"t\":52.906,\"k\":\"j\"},{\"t\":53.056,\"k\":\"f\"},{\"t\":53.245,\"k\":\"d\"},{\"t\":53.432,\"k\":\"k\"},{\"t\":53.669,\"k\":\"f\"},{\"t\":53.909,\"k\":\"j\"},{\"t\":54.678,\"k\":\"j\"},{\"t\":54.811,\"k\":\"f\"},{\"t\":54.929,\"k\":\"j\"},{\"t\":55.011,\"k\":\"f\"},{\"t\":55.127,\"k\":\"j\"},{\"t\":55.245,\"k\":\"d\"},{\"t\":55.379,\"k\":\"k\"},{\"t\":55.717,\"k\":\"j\"},{\"t\":55.861,\"k\":\"f\"},{\"t\":56,\"k\":\"k\"},{\"t\":56.187,\"k\":\"d\"},{\"t\":56.342,\"k\":\"j\"},{\"t\":56.62,\"k\":\"fk\"},{\"t\":56.898,\"k\":\"jd\"},{\"t\":57.506,\"k\":\"k\"},{\"t\":57.632,\"k\":\"f\"},{\"t\":57.697,\"k\":\"j\"},{\"t\":57.815,\"k\":\"d\"},{\"t\":57.953,\"k\":\"k\"},{\"t\":58.114,\"k\":\"f\"},{\"t\":58.264,\"k\":\"j\"},{\"t\":58.676,\"k\":\"j\"},{\"t\":58.844,\"k\":\"d\"},{\"t\":58.964,\"k\":\"j\"},{\"t\":59.131,\"k\":\"f\"},{\"t\":59.265,\"k\":\"k\"},{\"t\":59.533,\"k\":\"jd\"},{\"t\":59.797,\"k\":\"kf\"},{\"t\":60.61,\"k\":\"j\"},{\"t\":60.751,\"k\":\"f\"},{\"t\":60.819,\"k\":\"j\"},{\"t\":60.984,\"k\":\"d\"},{\"t\":61.046,\"k\":\"k\"},{\"t\":61.318,\"k\":\"j\"},{\"t\":61.735,\"k\":\"fjk\"},{\"t\":61.884,\"k\":\"kd\"},{\"t\":62.084,\"k\":\"jf\"},{\"t\":62.503,\"k\":\"kd\"},{\"t\":62.751,\"k\":\"jf\"},{\"t\":62.918,\"k\":\"kd\"},{\"t\":63.528,\"k\":\"j\"},{\"t\":63.692,\"k\":\"fj\"},{\"t\":63.948,\"k\":\"d\"},{\"t\":64.281,\"k\":\"j\"},{\"t\":64.414,\"k\":\"f\"},{\"t\":64.483,\"k\":\"j\"},{\"t\":64.697,\"k\":\"k\"},{\"t\":65.052,\"k\":\"j\"},{\"t\":65.179,\"k\":\"f\"},{\"t\":65.255,\"k\":\"kj\"},{\"t\":65.461,\"k\":\"d\"},{\"t\":65.776,\"k\":\"j\"},{\"t\":65.939,\"k\":\"fj\"},{\"t\":66.156,\"k\":\"k\"},{\"t\":66.314,\"k\":\"j\"},{\"t\":66.621,\"k\":\"k\"},{\"t\":66.751,\"k\":\"d\"},{\"t\":66.82,\"k\":\"j\"},{\"t\":67.01,\"k\":\"d\"},{\"t\":67.344,\"k\":\"j\"},{\"t\":67.473,\"k\":\"f\"},{\"t\":67.544,\"k\":\"j\"},{\"t\":67.712,\"k\":\"k\"},{\"t\":68.067,\"k\":\"j\"},{\"t\":68.223,\"k\":\"d\"},{\"t\":68.307,\"k\":\"k\"},{\"t\":68.509,\"k\":\"d\"},{\"t\":68.841,\"k\":\"j\"},{\"t\":69.023,\"k\":\"fj\"},{\"t\":69.268,\"k\":\"k\"},{\"t\":69.57,\"k\":\"j\"},{\"t\":69.736,\"k\":\"fj\"},{\"t\":69.952,\"k\":\"d\"},{\"t\":70.315,\"k\":\"f\"},{\"t\":70.408,\"k\":\"j\"},{\"t\":70.558,\"k\":\"j\"},{\"t\":70.709,\"k\":\"k\"},{\"t\":71.027,\"k\":\"j\"},{\"t\":71.194,\"k\":\"jf\"},{\"t\":71.427,\"k\":\"d\"},{\"t\":71.762,\"k\":\"k\"},{\"t\":71.963,\"k\":\"j\"},{\"t\":72.197,\"k\":\"d\"},{\"t\":72.462,\"k\":\"j\"},{\"t\":72.646,\"k\":\"f\"},{\"t\":72.727,\"k\":\"k\"},{\"t\":72.795,\"k\":\"k\"},{\"t\":72.983,\"k\":\"d\"},{\"t\":73.11,\"k\":\"j\"},{\"t\":73.277,\"k\":\"f\"},{\"t\":73.409,\"k\":\"k\"},{\"t\":73.57,\"k\":\"d\"},{\"t\":73.888,\"k\":\"k\"},{\"t\":74.041,\"k\":\"d\"},{\"t\":74.186,\"k\":\"k\"},{\"t\":74.33,\"k\":\"d\"},{\"t\":74.414,\"k\":\"k\"},{\"t\":74.519,\"k\":\"d\"},{\"t\":74.648,\"k\":\"j\"},{\"t\":74.781,\"k\":\"f\"},{\"t\":74.89,\"k\":\"j\"},{\"t\":75.042,\"k\":\"f\"},{\"t\":75.132,\"k\":\"j\"},{\"t\":75.299,\"k\":\"f\"},{\"t\":75.366,\"k\":\"j\"},{\"t\":75.548,\"k\":\"d\"},{\"t\":75.613,\"k\":\"k\"},{\"t\":75.781,\"k\":\"f\"},{\"t\":75.899,\"k\":\"j\"},{\"t\":76.013,\"k\":\"d\"},{\"t\":76.208,\"k\":\"j\"},{\"t\":76.46,\"k\":\"f\"},{\"t\":76.579,\"k\":\"k\"},{\"t\":76.734,\"k\":\"d\"},{\"t\":76.902,\"k\":\"j\"},{\"t\":77.051,\"k\":\"f\"},{\"t\":77.316,\"k\":\"k\"},{\"t\":77.527,\"k\":\"d\"},{\"t\":77.662,\"k\":\"j\"},{\"t\":77.87,\"k\":\"f\"},{\"t\":78.301,\"k\":\"d\",\"h\":{\"d\":81.16953586076355}},{\"t\":78.451,\"k\":\"j\"},{\"t\":78.56,\"k\":\"f\"},{\"t\":78.703,\"k\":\"k\"},{\"t\":78.868,\"k\":\"f\"},{\"t\":79.018,\"k\":\"j\"},{\"t\":79.425,\"k\":\"k\"},{\"t\":79.623,\"k\":\"f\"},{\"t\":79.766,\"k\":\"j\"},{\"t\":79.963,\"k\":\"f\"},{\"t\":80.105,\"k\":\"k\"},{\"t\":80.339,\"k\":\"f\"},{\"t\":80.544,\"k\":\"j\"},{\"t\":81.178,\"k\":\"k\"},{\"t\":81.321,\"k\":\"f\"},{\"t\":81.422,\"k\":\"j\"},{\"t\":81.543,\"k\":\"d\"},{\"t\":81.673,\"k\":\"k\"},{\"t\":81.822,\"k\":\"f\"},{\"t\":82.012,\"k\":\"j\"},{\"t\":82.356,\"k\":\"d\"},{\"t\":82.505,\"k\":\"k\"},{\"t\":82.751,\"k\":\"f\"},{\"t\":82.921,\"k\":\"jf\"},{\"t\":83.162,\"k\":\"kd\"},{\"t\":83.405,\"k\":\"jf\"},{\"t\":83.621,\"k\":\"kd\"},{\"t\":84.072,\"k\":\"j\"},{\"t\":84.143,\"k\":\"f\"},{\"t\":84.273,\"k\":\"k\"},{\"t\":84.326,\"k\":\"d\"},{\"t\":84.571,\"k\":\"j\"},{\"t\":84.726,\"k\":\"d\"},{\"t\":85.18,\"k\":\"jkdf\"},{\"t\":85.575,\"k\":\"j\"},{\"t\":85.743,\"k\":\"f\"},{\"t\":85.888,\"k\":\"k\"},{\"t\":85.947,\"k\":\"d\"},{\"t\":86.177,\"k\":\"j\"},{\"t\":86.574,\"k\":\"kjdf\"},{\"t\":87.038,\"k\":\"j\"},{\"t\":87.225,\"k\":\"fk\"},{\"t\":87.437,\"k\":\"d\"},{\"t\":87.506,\"k\":\"j\"},{\"t\":87.637,\"k\":\"k\",\"h\":{\"k\":89.66195412969971}},{\"t\":87.86,\"k\":\"f\"},{\"t\":87.995,\"k\":\"j\"},{\"t\":88.252,\"k\":\"d\"},{\"t\":88.413,\"k\":\"j\"},{\"t\":88.595,\"k\":\"f\"},{\"t\":88.801,\"k\":\"j\"},{\"t\":88.979,\"k\":\"d\"},{\"t\":89.176,\"k\":\"j\"},{\"t\":89.401,\"k\":\"f\"},{\"t\":89.542,\"k\":\"j\"},{\"t\":90.014,\"k\":\"d\"},{\"t\":90.136,\"k\":\"jf\"},{\"t\":90.299,\"k\":\"k\"},{\"t\":90.456,\"k\":\"j\"},{\"t\":90.557,\"k\":\"f\"},{\"t\":90.671,\"k\":\"d\"},{\"t\":90.938,\"k\":\"j\"},{\"t\":91.257,\"k\":\"j\"},{\"t\":91.399,\"k\":\"f\"},{\"t\":91.566,\"k\":\"k\"},{\"t\":91.711,\"k\":\"d\"},{\"t\":91.86,\"k\":\"j\"},{\"t\":91.917,\"k\":\"d\"},{\"t\":92.1,\"k\":\"k\"},{\"t\":92.164,\"k\":\"f\"},{\"t\":92.344,\"k\":\"jd\"},{\"t\":92.535,\"k\":\"k\"},{\"t\":92.882,\"k\":\"jf\"},{\"t\":93.18,\"k\":\"k\"},{\"t\":93.304,\"k\":\"d\"},{\"t\":93.383,\"k\":\"j\"},{\"t\":93.549,\"k\":\"f\"},{\"t\":93.684,\"k\":\"k\"},{\"t\":93.779,\"k\":\"d\"},{\"t\":93.942,\"k\":\"j\"},{\"t\":94.24,\"k\":\"f\"},{\"t\":94.317,\"k\":\"k\"},{\"t\":94.675,\"k\":\"jf\"},{\"t\":94.936,\"k\":\"dk\"},{\"t\":95.243,\"k\":\"j\"},{\"t\":95.352,\"k\":\"d\"},{\"t\":95.519,\"k\":\"kf\"},{\"t\":96.038,\"k\":\"j\"},{\"t\":96.148,\"k\":\"d\"},{\"t\":96.27,\"k\":\"k\"},{\"t\":96.354,\"k\":\"f\"},{\"t\":96.667,\"k\":\"d\"},{\"t\":96.828,\"k\":\"j\"},{\"t\":97.095,\"k\":\"jf\"},{\"t\":97.684,\"k\":\"jd\"},{\"t\":98.086,\"k\":\"kf\"},{\"t\":98.467,\"k\":\"jf\",\"h\":{\"j\":98.89696992752076,\"f\":98.88897003051758}},{\"t\":98.873,\"k\":\"kd\"},{\"t\":99.238,\"k\":\"j\"},{\"t\":99.365,\"k\":\"f\"},{\"t\":99.433,\"k\":\"k\"},{\"t\":99.488,\"k\":\"d\"},{\"t\":99.59,\"k\":\"f\"},{\"t\":99.781,\"k\":\"j\"},{\"t\":99.952,\"k\":\"f\"},{\"t\":100.04,\"k\":\"k\"},{\"t\":100.216,\"k\":\"d\"},{\"t\":100.353,\"k\":\"j\"},{\"t\":100.515,\"k\":\"f\"},{\"t\":100.585,\"k\":\"k\"},{\"t\":100.75,\"k\":\"d\"},{\"t\":100.871,\"k\":\"j\"},{\"t\":101.04,\"k\":\"f\"},{\"t\":101.103,\"k\":\"k\"},{\"t\":101.288,\"k\":\"d\"},{\"t\":101.436,\"k\":\"j\"},{\"t\":101.607,\"k\":\"d\"},{\"t\":101.876,\"k\":\"k\"},{\"t\":102.073,\"k\":\"f\"},{\"t\":102.234,\"k\":\"j\"},{\"t\":102.409,\"k\":\"d\"},{\"t\":102.593,\"k\":\"f\"},{\"t\":102.735,\"k\":\"j\"},{\"t\":102.923,\"k\":\"k\"},{\"t\":103.093,\"k\":\"f\"},{\"t\":103.255,\"k\":\"j\"},{\"t\":103.436,\"k\":\"d\"},{\"t\":103.562,\"k\":\"j\"},{\"t\":103.732,\"k\":\"f\"},{\"t\":103.91,\"k\":\"k\"},{\"t\":104.089,\"k\":\"d\"},{\"t\":104.222,\"k\":\"j\"},{\"t\":104.412,\"k\":\"f\"},{\"t\":104.57,\"k\":\"k\"},{\"t\":104.727,\"k\":\"d\"},{\"t\":104.899,\"k\":\"j\"},{\"t\":105.068,\"k\":\"f\"},{\"t\":105.219,\"k\":\"k\"},{\"t\":105.369,\"k\":\"d\"},{\"t\":105.523,\"k\":\"j\"},{\"t\":105.685,\"k\":\"f\"},{\"t\":105.849,\"k\":\"k\"},{\"t\":105.986,\"k\":\"d\"},{\"t\":106.197,\"k\":\"j\"},{\"t\":106.363,\"k\":\"f\"},{\"t\":106.519,\"k\":\"k\"},{\"t\":106.666,\"k\":\"d\"},{\"t\":106.869,\"k\":\"j\"},{\"t\":107.06,\"k\":\"f\"},{\"t\":107.226,\"k\":\"k\"},{\"t\":107.391,\"k\":\"d\"},{\"t\":107.601,\"k\":\"j\"},{\"t\":107.8,\"k\":\"f\"},{\"t\":107.95,\"k\":\"k\"},{\"t\":108.197,\"k\":\"k\"},{\"t\":108.362,\"k\":\"j\"},{\"t\":108.512,\"k\":\"f\"},{\"t\":108.674,\"k\":\"d\"},{\"t\":108.884,\"k\":\"k\"},{\"t\":109.038,\"k\":\"j\"},{\"t\":109.184,\"k\":\"f\"},{\"t\":109.28,\"k\":\"d\"},{\"t\":109.545,\"k\":\"k\"},{\"t\":109.691,\"k\":\"j\"},{\"t\":109.859,\"k\":\"f\"},{\"t\":109.963,\"k\":\"d\"},{\"t\":110.214,\"k\":\"k\"},{\"t\":110.363,\"k\":\"j\"},{\"t\":110.546,\"k\":\"f\"},{\"t\":110.706,\"k\":\"j\"},{\"t\":110.905,\"k\":\"d\"},{\"t\":111.086,\"k\":\"k\"},{\"t\":111.396,\"k\":\"f\"},{\"t\":111.709,\"k\":\"j\",\"h\":{\"j\":113.79255995994568}},{\"t\":112.442,\"k\":\"f\"},{\"t\":112.763,\"k\":\"d\"},{\"t\":113.017,\"k\":\"f\"},{\"t\":113.275,\"k\":\"k\"},{\"t\":113.867,\"k\":\"f\",\"h\":{\"f\":116.78895704959106}},{\"t\":114.169,\"k\":\"j\"},{\"t\":114.606,\"k\":\"k\"},{\"t\":114.823,\"k\":\"d\"},{\"t\":115.067,\"k\":\"j\"},{\"t\":115.407,\"k\":\"d\"},{\"t\":115.588,\"k\":\"k\"},{\"t\":115.898,\"k\":\"j\"},{\"t\":116.167,\"k\":\"d\"},{\"t\":116.979,\"k\":\"kd\"},{\"t\":117.354,\"k\":\"fj\"},{\"t\":117.697,\"k\":\"jd\"},{\"t\":118.069,\"k\":\"fk\"},{\"t\":118.474,\"k\":\"dfk\"},{\"t\":118.84,\"k\":\"kjd\"},{\"t\":119.241,\"k\":\"fj\"},{\"t\":119.658,\"k\":\"dk\"},{\"t\":119.973,\"k\":\"jf\",\"h\":{\"j\":120.93461503051758,\"f\":121.23910906484986}},{\"t\":121.281,\"k\":\"j\"},{\"t\":121.413,\"k\":\"f\"},{\"t\":121.5,\"k\":\"j\"},{\"t\":121.708,\"k\":\"d\"},{\"t\":121.905,\"k\":\"k\"},{\"t\":122.135,\"k\":\"j\"},{\"t\":122.373,\"k\":\"dk\"},{\"t\":122.779,\"k\":\"k\"},{\"t\":122.955,\"k\":\"k\"},{\"t\":123.077,\"k\":\"k\"},{\"t\":123.18,\"k\":\"f\"},{\"t\":123.31,\"k\":\"d\"},{\"t\":123.631,\"k\":\"d\"},{\"t\":123.814,\"k\":\"d\"},{\"t\":123.941,\"k\":\"f\"},{\"t\":124.04,\"k\":\"j\"},{\"t\":124.157,\"k\":\"k\"},{\"t\":124.426,\"k\":\"j\"},{\"t\":124.607,\"k\":\"j\"},{\"t\":124.737,\"k\":\"f\"},{\"t\":124.899,\"k\":\"d\"},{\"t\":125.239,\"k\":\"f\"},{\"t\":125.431,\"k\":\"f\"},{\"t\":125.579,\"k\":\"j\"},{\"t\":125.726,\"k\":\"k\"},{\"t\":125.981,\"k\":\"k\"},{\"t\":126.121,\"k\":\"k\"},{\"t\":126.227,\"k\":\"f\"},{\"t\":126.355,\"k\":\"d\"},{\"t\":126.648,\"k\":\"j\"},{\"t\":126.81,\"k\":\"j\"},{\"t\":126.952,\"k\":\"f\"},{\"t\":127.093,\"k\":\"d\"},{\"t\":127.377,\"k\":\"j\"},{\"t\":127.55,\"k\":\"j\"},{\"t\":127.711,\"k\":\"f\"},{\"t\":127.827,\"k\":\"j\"},{\"t\":127.952,\"k\":\"k\"},{\"t\":128.257,\"k\":\"j\"},{\"t\":128.418,\"k\":\"f\"},{\"t\":128.729,\"k\":\"k\"},{\"t\":128.884,\"k\":\"k\"},{\"t\":129.012,\"k\":\"j\"},{\"t\":129.087,\"k\":\"f\"},{\"t\":129.21,\"k\":\"d\"},{\"t\":129.557,\"k\":\"d\"},{\"t\":129.736,\"k\":\"d\"},{\"t\":129.881,\"k\":\"f\"},{\"t\":129.945,\"k\":\"j\"},{\"t\":130.093,\"k\":\"k\"},{\"t\":130.344,\"k\":\"j\"},{\"t\":130.484,\"k\":\"f\"},{\"t\":130.636,\"k\":\"dk\"},{\"t\":130.736,\"k\":\"j\"},{\"t\":131.051,\"k\":\"kf\"},{\"t\":131.404,\"k\":\"jf\"},{\"t\":131.769,\"k\":\"k\"},{\"t\":131.921,\"k\":\"d\"},{\"t\":132.052,\"k\":\"k\"},{\"t\":132.136,\"k\":\"j\"},{\"t\":132.362,\"k\":\"f\"},{\"t\":132.533,\"k\":\"k\"},{\"t\":132.638,\"k\":\"d\"},{\"t\":132.805,\"k\":\"j\"},{\"t\":133.083,\"k\":\"j\"},{\"t\":133.236,\"k\":\"f\"},{\"t\":133.369,\"k\":\"j\"},{\"t\":133.521,\"k\":\"f\"},{\"t\":133.633,\"k\":\"j\"},{\"t\":133.775,\"k\":\"f\"},{\"t\":133.87,\"k\":\"j\"},{\"t\":133.991,\"k\":\"d\"},{\"t\":134.334,\"k\":\"dk\"},{\"t\":134.753,\"k\":\"k\"},{\"t\":134.857,\"k\":\"fj\"},{\"t\":134.992,\"k\":\"d\"},{\"t\":135.134,\"k\":\"k\"},{\"t\":135.315,\"k\":\"jf\"},{\"t\":135.489,\"k\":\"d\"},{\"t\":135.753,\"k\":\"j\"},{\"t\":135.921,\"k\":\"f\"},{\"t\":135.991,\"k\":\"k\"},{\"t\":136.231,\"k\":\"d\"},{\"t\":136.39,\"k\":\"j\"},{\"t\":136.635,\"k\":\"f\"},{\"t\":136.718,\"k\":\"k\"},{\"t\":136.952,\"k\":\"d\"},{\"t\":137.117,\"k\":\"jf\",\"h\":{\"j\":137.47730301335145,\"f\":137.48830293133545}},{\"t\":137.454,\"k\":\"kd\"},{\"t\":137.756,\"k\":\"k\"},{\"t\":137.825,\"k\":\"d\"},{\"t\":137.954,\"k\":\"fj\"},{\"t\":138.176,\"k\":\"k\"},{\"t\":138.354,\"k\":\"j\"},{\"t\":138.441,\"k\":\"d\"},{\"t\":138.756,\"k\":\"j\"},{\"t\":138.906,\"k\":\"f\"},{\"t\":139.027,\"k\":\"k\"},{\"t\":139.26,\"k\":\"dj\"},{\"t\":139.512,\"k\":\"kf\"},{\"t\":139.757,\"k\":\"j\"},{\"t\":139.821,\"k\":\"d\"},{\"t\":139.986,\"k\":\"kf\"},{\"t\":140.414,\"k\":\"j\"},{\"t\":140.545,\"k\":\"f\"},{\"t\":140.673,\"k\":\"k\"},{\"t\":140.843,\"k\":\"j\"},{\"t\":140.947,\"k\":\"d\"},{\"t\":141.193,\"k\":\"j\"},{\"t\":141.33,\"k\":\"f\"},{\"t\":141.64,\"k\":\"k\"},{\"t\":141.808,\"k\":\"d\"},{\"t\":141.942,\"k\":\"j\"},{\"t\":142.123,\"k\":\"f\"},{\"t\":142.214,\"k\":\"j\"},{\"t\":142.489,\"k\":\"d\"},{\"t\":142.583,\"k\":\"k\"},{\"t\":142.809,\"k\":\"fj\"},{\"t\":143.027,\"k\":\"dk\"},{\"t\":143.528,\"k\":\"k\",\"h\":{\"k\":144.3841849408722}},{\"t\":143.881,\"k\":\"f\"},{\"t\":144.065,\"k\":\"d\"},{\"t\":144.244,\"k\":\"j\"},{\"t\":144.549,\"k\":\"jf\"},{\"t\":144.869,\"k\":\"dk\"},{\"t\":145.214,\"k\":\"k\"},{\"t\":145.333,\"k\":\"j\"},{\"t\":145.549,\"k\":\"f\"},{\"t\":145.735,\"k\":\"k\"},{\"t\":146.008,\"k\":\"j\"},{\"t\":146.367,\"k\":\"jdfk\"},{\"t\":146.657,\"k\":\"j\"},{\"t\":146.771,\"k\":\"d\"},{\"t\":146.901,\"k\":\"k\"},{\"t\":147.054,\"k\":\"f\"},{\"t\":147.153,\"k\":\"j\"},{\"t\":147.284,\"k\":\"d\"},{\"t\":147.57,\"k\":\"j\"},{\"t\":147.804,\"k\":\"f\"},{\"t\":147.916,\"k\":\"k\"},{\"t\":148.087,\"k\":\"d\"},{\"t\":148.277,\"k\":\"j\"},{\"t\":148.435,\"k\":\"f\"},{\"t\":148.501,\"k\":\"k\"},{\"t\":148.68,\"k\":\"d\"},{\"t\":148.852,\"k\":\"j\"},{\"t\":149.378,\"k\":\"d\",\"h\":{\"d\":152.2018100228882}},{\"t\":149.52,\"k\":\"j\"},{\"t\":149.684,\"k\":\"f\"},{\"t\":149.756,\"k\":\"k\"},{\"t\":149.936,\"k\":\"f\"},{\"t\":150.056,\"k\":\"j\"},{\"t\":150.205,\"k\":\"f\"},{\"t\":150.535,\"k\":\"j\"},{\"t\":150.702,\"k\":\"f\"},{\"t\":150.851,\"k\":\"k\"},{\"t\":151.035,\"k\":\"f\"},{\"t\":151.289,\"k\":\"j\"},{\"t\":151.506,\"k\":\"f\"},{\"t\":151.654,\"k\":\"k\"},{\"t\":151.905,\"k\":\"j\"},{\"t\":152.341,\"k\":\"k\"},{\"t\":152.459,\"k\":\"f\"},{\"t\":152.559,\"k\":\"j\"},{\"t\":152.659,\"k\":\"d\"},{\"t\":152.803,\"k\":\"k\"},{\"t\":152.958,\"k\":\"f\"},{\"t\":153.09,\"k\":\"j\"},{\"t\":153.417,\"k\":\"fj\"},{\"t\":153.574,\"k\":\"dk\"},{\"t\":153.805,\"k\":\"jf\"},{\"t\":154.134,\"k\":\"k\"},{\"t\":154.418,\"k\":\"fd\"},{\"t\":154.637,\"k\":\"j\"},{\"t\":155.102,\"k\":\"jdfk\"},{\"t\":155.445,\"k\":\"j\"},{\"t\":155.589,\"k\":\"f\"},{\"t\":155.755,\"k\":\"k\"},{\"t\":155.872,\"k\":\"d\"},{\"t\":156.024,\"k\":\"j\"},{\"t\":156.193,\"k\":\"f\"},{\"t\":156.341,\"k\":\"k\"},{\"t\":157.074,\"k\":\"jk\"},{\"t\":157.376,\"k\":\"df\"},{\"t\":157.786,\"k\":\"jf\"},{\"t\":158.148,\"k\":\"kd\"},{\"t\":158.491,\"k\":\"jf\"},{\"t\":158.649,\"k\":\"j\"},{\"t\":158.713,\"k\":\"f\"},{\"t\":158.83,\"k\":\"j\"},{\"t\":158.964,\"k\":\"d\"},{\"t\":159.399,\"k\":\"j\"},{\"t\":159.498,\"k\":\"f\"},{\"t\":159.598,\"k\":\"j\"},{\"t\":159.662,\"k\":\"f\"},{\"t\":159.929,\"k\":\"k\"},{\"t\":160.149,\"k\":\"j\"},{\"t\":160.566,\"k\":\"j\"},{\"t\":160.716,\"k\":\"d\"},{\"t\":160.85,\"k\":\"k\"},{\"t\":160.927,\"k\":\"f\"},{\"t\":161.279,\"k\":\"k\"},{\"t\":161.436,\"k\":\"jf\"},{\"t\":161.598,\"k\":\"d\"},{\"t\":161.699,\"k\":\"f\"},{\"t\":162.284,\"k\":\"j\"},{\"t\":162.433,\"k\":\"f\"},{\"t\":162.546,\"k\":\"j\"},{\"t\":162.7,\"k\":\"k\"},{\"t\":162.916,\"k\":\"j\"},{\"t\":163.198,\"k\":\"d\"},{\"t\":163.333,\"k\":\"j\"},{\"t\":163.508,\"k\":\"f\"},{\"t\":163.745,\"k\":\"k\"},{\"t\":164.212,\"k\":\"k\"},{\"t\":164.387,\"k\":\"f\"},{\"t\":164.558,\"k\":\"j\"},{\"t\":164.686,\"k\":\"d\"},{\"t\":164.814,\"k\":\"j\"},{\"t\":164.95,\"k\":\"f\"},{\"t\":165.07,\"k\":\"k\"},{\"t\":165.207,\"k\":\"d\"},{\"t\":165.353,\"k\":\"j\"},{\"t\":165.48,\"k\":\"f\"},{\"t\":165.608,\"k\":\"k\"},{\"t\":165.766,\"k\":\"d\"},{\"t\":165.891,\"k\":\"j\"},{\"t\":166.049,\"k\":\"f\"},{\"t\":166.151,\"k\":\"k\"},{\"t\":166.309,\"k\":\"d\"},{\"t\":166.456,\"k\":\"j\"},{\"t\":166.549,\"k\":\"f\"},{\"t\":166.679,\"k\":\"k\"},{\"t\":166.874,\"k\":\"d\"},{\"t\":166.998,\"k\":\"j\"},{\"t\":167.15,\"k\":\"f\"},{\"t\":167.232,\"k\":\"k\"},{\"t\":167.391,\"k\":\"d\"},{\"t\":167.452,\"k\":\"j\"},{\"t\":167.653,\"k\":\"f\"},{\"t\":167.886,\"k\":\"k\"},{\"t\":168.642,\"k\":\"fkd\"},{\"t\":168.915,\"k\":\"jd\"},{\"t\":169.193,\"k\":\"kf\"},{\"t\":169.458,\"k\":\"jd\"},{\"t\":169.714,\"k\":\"kf\"},{\"t\":170.085,\"k\":\"j\"},{\"t\":170.207,\"k\":\"d\"},{\"t\":170.307,\"k\":\"k\"},{\"t\":170.451,\"k\":\"f\"},{\"t\":170.552,\"k\":\"j\"},{\"t\":170.651,\"k\":\"d\"},{\"t\":170.793,\"k\":\"k\"},{\"t\":170.936,\"k\":\"f\"},{\"t\":171.041,\"k\":\"j\"},{\"t\":171.125,\"k\":\"d\"},{\"t\":171.308,\"k\":\"k\"},{\"t\":171.474,\"k\":\"f\"},{\"t\":171.575,\"k\":\"j\"},{\"t\":171.677,\"k\":\"d\"},{\"t\":171.835,\"k\":\"j\"},{\"t\":171.985,\"k\":\"f\"},{\"t\":172.108,\"k\":\"j\"},{\"t\":172.223,\"k\":\"d\"},{\"t\":172.329,\"k\":\"j\"},{\"t\":172.44,\"k\":\"f\"},{\"t\":172.581,\"k\":\"k\"},{\"t\":172.889,\"k\":\"j\"},{\"t\":173.007,\"k\":\"f\"},{\"t\":173.147,\"k\":\"j\"},{\"t\":173.303,\"k\":\"d\"},{\"t\":173.425,\"k\":\"k\"},{\"t\":173.589,\"k\":\"f\"},{\"t\":173.696,\"k\":\"j\"},{\"t\":173.859,\"k\":\"d\"},{\"t\":173.979,\"k\":\"k\"},{\"t\":174.171,\"k\":\"f\"},{\"t\":174.246,\"k\":\"j\"},{\"t\":174.459,\"k\":\"d\"},{\"t\":174.535,\"k\":\"k\"},{\"t\":174.709,\"k\":\"f\"},{\"t\":174.799,\"k\":\"j\"},{\"t\":174.983,\"k\":\"d\"},{\"t\":175.107,\"k\":\"k\"},{\"t\":175.293,\"k\":\"f\"},{\"t\":175.417,\"k\":\"j\"},{\"t\":175.567,\"k\":\"d\"},{\"t\":175.975,\"k\":\"j\"},{\"t\":176.102,\"k\":\"f\"},{\"t\":176.199,\"k\":\"k\"},{\"t\":176.349,\"k\":\"d\"},{\"t\":176.533,\"k\":\"j\"},{\"t\":176.681,\"k\":\"f\"},{\"t\":176.828,\"k\":\"j\"},{\"t\":176.973,\"k\":\"d\"},{\"t\":177.113,\"k\":\"k\"},{\"t\":177.25,\"k\":\"f\"},{\"t\":177.349,\"k\":\"j\"},{\"t\":177.557,\"k\":\"d\"},{\"t\":177.706,\"k\":\"k\"},{\"t\":177.873,\"k\":\"d\"},{\"t\":178.053,\"k\":\"j\"},{\"t\":178.219,\"k\":\"f\"},{\"t\":178.384,\"k\":\"k\"},{\"t\":178.543,\"k\":\"d\"},{\"t\":178.744,\"k\":\"j\"},{\"t\":178.943,\"k\":\"f\"},{\"t\":179.084,\"k\":\"k\"},{\"t\":179.209,\"k\":\"d\"},{\"t\":179.441,\"k\":\"j\"},{\"t\":179.719,\"k\":\"f\"},{\"t\":179.843,\"k\":\"k\"},{\"t\":179.994,\"k\":\"d\"},{\"t\":180.16,\"k\":\"j\"},{\"t\":180.355,\"k\":\"f\"},{\"t\":180.554,\"k\":\"k\"},{\"t\":180.721,\"k\":\"k\"},{\"t\":180.794,\"k\":\"j\"},{\"t\":181.035,\"k\":\"d\"},{\"t\":181.137,\"k\":\"k\"},{\"t\":181.189,\"k\":\"f\"},{\"t\":182.215,\"k\":\"j\"},{\"t\":182.274,\"k\":\"k\"},{\"t\":182.312,\"k\":\"fd\"},{\"t\":182.391,\"k\":\"jk\"},{\"t\":182.714,\"k\":\"jk\"},{\"t\":182.806,\"k\":\"df\"},{\"t\":182.89,\"k\":\"jk\"},{\"t\":183.005,\"k\":\"fd\"},{\"t\":183.638,\"k\":\"k\",\"h\":{\"k\":183.99045797138976}},{\"t\":183.695,\"k\":\"d\",\"h\":{\"d\":183.98295803814696}},{\"t\":183.974,\"k\":\"jf\",\"h\":{\"j\":184.34739399904632,\"f\":184.33339406008147}},{\"t\":184.364,\"k\":\"dk\",\"h\":{\"d\":184.6914269742508,\"k\":184.6599269923706}},{\"t\":184.774,\"k\":\"k\",\"h\":{\"k\":185.21541106198882}},{\"t\":185.151,\"k\":\"d\",\"h\":{\"d\":185.52406302861024}},{\"t\":185.476,\"k\":\"j\",\"h\":{\"j\":185.81710397901915}},{\"t\":185.843,\"k\":\"f\",\"h\":{\"f\":186.11746398188018}},{\"t\":186.215,\"k\":\"dk\",\"h\":{\"d\":186.40901200476839,\"k\":186.4536909818802}},{\"t\":186.525,\"k\":\"jf\",\"h\":{\"j\":186.80093504577636,\"f\":186.8094350257492}},{\"t\":186.927,\"k\":\"dk\",\"h\":{\"d\":187.107723038147,\"k\":187.14272300476838}},{\"t\":187.302,\"k\":\"jd\",\"h\":{\"j\":187.51100598664857,\"d\":187.4865060934601}},{\"t\":187.685,\"k\":\"fk\",\"h\":{\"f\":187.85361796185302}},{\"t\":188.094,\"k\":\"dj\",\"h\":{\"d\":188.31050705912781,\"j\":188.30300700667573}},{\"t\":188.479,\"k\":\"kf\",\"h\":{\"f\":188.65414492084503}},{\"t\":188.874,\"k\":\"kd\"},{\"t\":189.028,\"k\":\"j\"},{\"t\":189.121,\"k\":\"f\"},{\"t\":189.272,\"k\":\"k\"},{\"t\":189.305,\"k\":\"d\"},{\"t\":189.59,\"k\":\"j\",\"h\":{\"j\":189.82239000667573}},{\"t\":189.771,\"k\":\"d\"},{\"t\":189.978,\"k\":\"k\",\"h\":{\"k\":190.22141593419647}},{\"t\":190.197,\"k\":\"f\",\"h\":{\"f\":190.38175608678435}},{\"t\":190.354,\"k\":\"j\",\"h\":{\"j\":190.57389404959108}},{\"t\":190.567,\"k\":\"d\",\"h\":{\"d\":190.78961399427794}},{\"t\":190.732,\"k\":\"j\",\"h\":{\"j\":190.90018707534028}},{\"t\":190.897,\"k\":\"f\",\"h\":{\"f\":191.1219359265671}},{\"t\":191.065,\"k\":\"k\",\"h\":{\"k\":191.2881089189377}},{\"t\":191.257,\"k\":\"d\",\"h\":{\"d\":191.45566802002716}},{\"t\":191.414,\"k\":\"j\",\"h\":{\"j\":191.62558296566772}},{\"t\":191.631,\"k\":\"f\",\"h\":{\"f\":191.82565710585786}},{\"t\":191.814,\"k\":\"k\",\"h\":{\"k\":192.01712100667572}},{\"t\":191.997,\"k\":\"d\",\"h\":{\"d\":192.23390899809266}},{\"t\":192.174,\"k\":\"j\",\"h\":{\"j\":192.38207598378753}},{\"t\":192.375,\"k\":\"f\"},{\"t\":192.525,\"k\":\"k\",\"h\":{\"k\":192.74141306866454}},{\"t\":192.718,\"k\":\"d\",\"h\":{\"d\":192.95798605912782}},{\"t\":192.917,\"k\":\"j\",\"h\":{\"j\":193.15686302861022}},{\"t\":193.164,\"k\":\"f\",\"h\":{\"f\":193.3417600219345}},{\"t\":193.301,\"k\":\"k\",\"h\":{\"k\":193.52178095326997}},{\"t\":193.48,\"k\":\"d\",\"h\":{\"d\":193.6828410333786}},{\"t\":193.659,\"k\":\"j\",\"h\":{\"j\":193.8499520362396}},{\"t\":193.833,\"k\":\"f\",\"h\":{\"f\":194.04711699427796}},{\"t\":193.999,\"k\":\"k\",\"h\":{\"k\":194.21151801239776}},{\"t\":194.208,\"k\":\"d\"},{\"t\":194.326,\"k\":\"f\",\"h\":{\"f\":194.50107394182587}},{\"t\":194.461,\"k\":\"j\"},{\"t\":194.618,\"k\":\"dk\",\"h\":{\"d\":194.80143992847442,\"k\":194.80243997520446}},{\"t\":194.784,\"k\":\"fj\",\"h\":{\"f\":194.94960001239775,\"j\":194.959600002861}},{\"t\":194.968,\"k\":\"d\"},{\"t\":195.049,\"k\":\"j\"},{\"t\":195.1,\"k\":\"f\"},{\"t\":195.178,\"k\":\"dk\"},{\"t\":195.335,\"k\":\"jf\"},{\"t\":195.935,\"k\":\"k\",\"h\":{\"k\":196.19833801716615}},{\"t\":196.12,\"k\":\"d\",\"h\":{\"d\":196.3062569217987}},{\"t\":196.287,\"k\":\"j\",\"h\":{\"j\":196.48547800858307}},{\"t\":196.46,\"k\":\"f\"},{\"t\":196.653,\"k\":\"k\",\"h\":{\"k\":196.8168080267029}},{\"t\":196.826,\"k\":\"d\",\"h\":{\"d\":197.02693602193452}},{\"t\":197.011,\"k\":\"j\"},{\"t\":197.204,\"k\":\"f\"},{\"t\":197.413,\"k\":\"k\",\"h\":{\"k\":197.60295600476837}},{\"t\":197.595,\"k\":\"d\",\"h\":{\"d\":197.76983602861023}},{\"t\":197.763,\"k\":\"j\",\"h\":{\"j\":197.932965}},{\"t\":197.964,\"k\":\"f\",\"h\":{\"f\":198.1654270076294}},{\"t\":198.141,\"k\":\"k\",\"h\":{\"k\":198.331443}},{\"t\":198.333,\"k\":\"d\"},{\"t\":198.488,\"k\":\"j\",\"h\":{\"j\":198.66640398950958}},{\"t\":198.671,\"k\":\"f\",\"h\":{\"f\":198.8405139256134}},{\"t\":198.856,\"k\":\"k\"},{\"t\":199.02,\"k\":\"d\",\"h\":{\"d\":199.17959806580353}},{\"t\":199.207,\"k\":\"j\",\"h\":{\"j\":199.40551496471406}},{\"t\":199.449,\"k\":\"f\"},{\"t\":199.618,\"k\":\"k\",\"h\":{\"k\":199.7847939475479}},{\"t\":199.788,\"k\":\"d\"},{\"t\":199.982,\"k\":\"jf\"},{\"t\":200.15,\"k\":\"dk\",\"h\":{\"d\":200.3345120371933}},{\"t\":200.351,\"k\":\"jf\",\"h\":{\"j\":200.55289298664857,\"f\":200.559892956131}},{\"t\":200.592,\"k\":\"dk\",\"h\":{\"d\":200.7588808884201,\"k\":200.75188091893767}},{\"t\":200.764,\"k\":\"j\"},{\"t\":200.91,\"k\":\"f\"},{\"t\":201.099,\"k\":\"k\"},{\"t\":201.268,\"k\":\"j\"},{\"t\":201.486,\"k\":\"dj\",\"h\":{\"d\":201.7015859361038,\"j\":201.6850859399185}},{\"t\":201.801,\"k\":\"kf\",\"h\":{\"k\":202.0017230219345,\"f\":202.0077229446869}},{\"t\":202.143,\"k\":\"jd\",\"h\":{\"j\":202.352434043869,\"d\":202.32127604196168}},{\"t\":202.536,\"k\":\"fk\"},{\"t\":202.921,\"k\":\"j\",\"h\":{\"j\":203.11295296376036}},{\"t\":203.118,\"k\":\"d\"},{\"t\":203.297,\"k\":\"k\",\"h\":{\"k\":203.51302509346007}},{\"t\":203.521,\"k\":\"f\"},{\"t\":203.662,\"k\":\"j\",\"h\":{\"j\":203.86161505817412}},{\"t\":203.854,\"k\":\"d\",\"h\":{\"d\":204.0350039370575}},{\"t\":204.047,\"k\":\"k\",\"h\":{\"k\":204.27185998664856}},{\"t\":204.234,\"k\":\"f\"},{\"t\":204.421,\"k\":\"j\",\"h\":{\"j\":204.64717398474122}},{\"t\":204.613,\"k\":\"d\"},{\"t\":204.765,\"k\":\"f\",\"h\":{\"f\":205.0218610190735}},{\"t\":204.965,\"k\":\"k\"},{\"t\":205.129,\"k\":\"d\",\"h\":{\"d\":205.35569209727478}},{\"t\":205.313,\"k\":\"j\"},{\"t\":205.481,\"k\":\"k\",\"h\":{\"k\":205.75605990558626}},{\"t\":205.706,\"k\":\"f\"},{\"t\":205.847,\"k\":\"d\",\"h\":{\"d\":206.2045260076294}},{\"t\":206.048,\"k\":\"j\"},{\"t\":206.259,\"k\":\"j\",\"h\":{\"j\":206.51574992847443}},{\"t\":206.449,\"k\":\"f\"},{\"t\":206.615,\"k\":\"f\",\"h\":{\"f\":206.84003009918212}},{\"t\":206.807,\"k\":\"j\"},{\"t\":206.974,\"k\":\"kd\"},{\"t\":207.149,\"k\":\"jf\"},{\"t\":207.437,\"k\":\"df\"},{\"t\":207.609,\"k\":\"df\"},{\"t\":207.798,\"k\":\"jk\"},{\"t\":207.983,\"k\":\"jk\"},{\"t\":208.168,\"k\":\"f\"},{\"t\":208.233,\"k\":\"j\"},{\"t\":208.301,\"k\":\"d\"},{\"t\":208.382,\"k\":\"k\"},{\"t\":208.45,\"k\":\"f\"},{\"t\":208.543,\"k\":\"j\"},{\"t\":208.81,\"k\":\"dfjk\"},{\"t\":209.068,\"k\":\"j\"},{\"t\":209.201,\"k\":\"f\"},{\"t\":209.316,\"k\":\"k\"},{\"t\":209.417,\"k\":\"d\"},{\"t\":209.568,\"k\":\"j\"},{\"t\":209.66,\"k\":\"f\"},{\"t\":209.728,\"k\":\"k\"},{\"t\":209.777,\"k\":\"d\"},{\"t\":210.032,\"k\":\"j\"},{\"t\":210.128,\"k\":\"kdf\"},{\"t\":210.344,\"k\":\"j\"},{\"t\":210.509,\"k\":\"j\"},{\"t\":210.677,\"k\":\"f\"},{\"t\":210.733,\"k\":\"k\"},{\"t\":210.83,\"k\":\"d\"},{\"t\":210.866,\"k\":\"j\"},{\"t\":210.921,\"k\":\"f\"},{\"t\":211.107,\"k\":\"j\"},{\"t\":211.278,\"k\":\"j\"},{\"t\":211.392,\"k\":\"f\"},{\"t\":211.482,\"k\":\"dj\"},{\"t\":211.62,\"k\":\"k\"},{\"t\":211.751,\"k\":\"j\"},{\"t\":211.851,\"k\":\"f\"},{\"t\":211.997,\"k\":\"kd\"},{\"t\":212.135,\"k\":\"j\"},{\"t\":212.249,\"k\":\"f\"},{\"t\":212.536,\"k\":\"jkdf\"}]}",
  "mapId": "7tEjnooCjR9pgVHDjKQ9tp",
  "verified": false,
  "clonedFrom": "",
  "createdAt": 1662394914,
  "updatedAt": 1668057260
}
