{
  "id": "3iiBapemxJF1dvb1TjyVEF",
  "songId": "3WNuDCWV3E9pyGDN3eHALj",
  "title": "",
  "subtitle": "",
  "startAt": 0,
  "endAt": 0,
  "keys": 4,
  "difficulty": 10,
  "length": 235.363,
  "noteCount": 1490,
  "bpm": 0,
  "svCount": 0,
  "visualizerName": "",
  "visibility": "public",
  "isImported": false,
  "importedFrom": "",
  "importRef": "",
  "importIsOriginal": false,
  "mapping": "{\"version\":1,\"title\":\"\",\"startAt\":null,\"endAt\":null,\"keys\":4,\"difficulty\":10,\"length\":235.363,\"noteCount\":1490,\"visualizerName\":\"\",\"clonedFrom\":\"\",\"mappings\":[{\"t\":1.833,\"k\":\"f\"},{\"t\":2.207,\"k\":\"j\"},{\"t\":2.464,\"k\":\"d\"},{\"t\":2.582,\"k\":\"k\"},{\"t\":2.682,\"k\":\"f\"},{\"t\":2.782,\"k\":\"j\"},{\"t\":2.881,\"k\":\"d\"},{\"t\":3.047,\"k\":\"kf\"},{\"t\":3.214,\"k\":\"j\"},{\"t\":3.431,\"k\":\"k\"},{\"t\":3.515,\"k\":\"j\"},{\"t\":3.565,\"k\":\"d\"},{\"t\":3.698,\"k\":\"f\"},{\"t\":3.848,\"k\":\"k\"},{\"t\":3.948,\"k\":\"dj\"},{\"t\":4.098,\"k\":\"f\"},{\"t\":4.248,\"k\":\"k\",\"h\":{\"k\":24.94586124561428}},{\"t\":4.331,\"k\":\"d\",\"h\":{\"d\":24.96286120555996}},{\"t\":6.981,\"k\":\"jf\"},{\"t\":9.698,\"k\":\"jf\"},{\"t\":12.365,\"k\":\"jf\"},{\"t\":13.215,\"k\":\"fj\"},{\"t\":13.831,\"k\":\"jf\"},{\"t\":14.215,\"k\":\"fj\"},{\"t\":14.498,\"k\":\"jf\"},{\"t\":14.648,\"k\":\"j\"},{\"t\":14.698,\"k\":\"f\"},{\"t\":14.881,\"k\":\"j\"},{\"t\":14.984,\"k\":\"f\"},{\"t\":15.097,\"k\":\"j\"},{\"t\":15.197,\"k\":\"f\"},{\"t\":15.314,\"k\":\"j\"},{\"t\":15.448,\"k\":\"f\"},{\"t\":15.565,\"k\":\"j\"},{\"t\":15.681,\"k\":\"f\"},{\"t\":15.781,\"k\":\"j\"},{\"t\":15.898,\"k\":\"f\"},{\"t\":16.015,\"k\":\"j\"},{\"t\":16.131,\"k\":\"f\"},{\"t\":16.248,\"k\":\"j\"},{\"t\":16.363,\"k\":\"f\"},{\"t\":16.481,\"k\":\"j\"},{\"t\":16.613,\"k\":\"f\"},{\"t\":16.713,\"k\":\"j\"},{\"t\":16.83,\"k\":\"f\"},{\"t\":16.93,\"k\":\"j\"},{\"t\":17.064,\"k\":\"f\"},{\"t\":17.315,\"k\":\"jf\"},{\"t\":17.631,\"k\":\"j\"},{\"t\":17.698,\"k\":\"f\"},{\"t\":17.83,\"k\":\"j\"},{\"t\":17.946,\"k\":\"f\"},{\"t\":18.047,\"k\":\"j\"},{\"t\":18.162,\"k\":\"f\"},{\"t\":18.278,\"k\":\"j\"},{\"t\":18.38,\"k\":\"f\"},{\"t\":18.513,\"k\":\"j\"},{\"t\":18.631,\"k\":\"f\"},{\"t\":18.748,\"k\":\"j\"},{\"t\":18.847,\"k\":\"f\"},{\"t\":18.965,\"k\":\"j\"},{\"t\":19.096,\"k\":\"f\"},{\"t\":19.197,\"k\":\"j\"},{\"t\":19.297,\"k\":\"f\"},{\"t\":19.414,\"k\":\"j\"},{\"t\":19.565,\"k\":\"f\"},{\"t\":19.647,\"k\":\"j\"},{\"t\":19.748,\"k\":\"f\"},{\"t\":19.946,\"k\":\"jf\"},{\"t\":20.197,\"k\":\"j\"},{\"t\":20.313,\"k\":\"f\"},{\"t\":20.43,\"k\":\"j\"},{\"t\":20.563,\"k\":\"f\"},{\"t\":20.681,\"k\":\"j\"},{\"t\":20.797,\"k\":\"f\"},{\"t\":20.914,\"k\":\"j\"},{\"t\":21.014,\"k\":\"f\"},{\"t\":21.131,\"k\":\"jf\"},{\"t\":21.349,\"k\":\"j\"},{\"t\":21.413,\"k\":\"f\"},{\"t\":21.598,\"k\":\"j\"},{\"t\":21.664,\"k\":\"f\"},{\"t\":21.815,\"k\":\"j\"},{\"t\":21.913,\"k\":\"f\"},{\"t\":22.013,\"k\":\"j\"},{\"t\":22.147,\"k\":\"f\"},{\"t\":22.231,\"k\":\"j\"},{\"t\":22.297,\"k\":\"f\"},{\"t\":22.614,\"k\":\"jf\"},{\"t\":23.264,\"k\":\"fj\"},{\"t\":23.914,\"k\":\"jf\"},{\"t\":24.247,\"k\":\"jf\"},{\"t\":24.614,\"k\":\"jf\"},{\"t\":24.915,\"k\":\"jf\"},{\"t\":25.13,\"k\":\"k\"},{\"t\":25.18,\"k\":\"d\"},{\"t\":25.33,\"k\":\"jf\"},{\"t\":25.496,\"k\":\"k\"},{\"t\":25.597,\"k\":\"d\"},{\"t\":25.748,\"k\":\"f\"},{\"t\":25.861,\"k\":\"j\"},{\"t\":25.995,\"k\":\"j\"},{\"t\":26.112,\"k\":\"dk\"},{\"t\":26.296,\"k\":\"f\"},{\"t\":26.361,\"k\":\"j\"},{\"t\":26.478,\"k\":\"d\"},{\"t\":26.545,\"k\":\"k\"},{\"t\":26.647,\"k\":\"f\"},{\"t\":26.697,\"k\":\"j\"},{\"t\":26.846,\"k\":\"kd\"},{\"t\":27.012,\"k\":\"f\"},{\"t\":27.213,\"k\":\"kd\"},{\"t\":27.48,\"k\":\"fj\"},{\"t\":27.63,\"k\":\"kd\"},{\"t\":27.813,\"k\":\"fj\"},{\"t\":28.013,\"k\":\"k\"},{\"t\":28.145,\"k\":\"d\"},{\"t\":28.264,\"k\":\"f\"},{\"t\":28.38,\"k\":\"j\"},{\"t\":28.513,\"k\":\"k\"},{\"t\":28.63,\"k\":\"jd\"},{\"t\":28.797,\"k\":\"f\"},{\"t\":28.88,\"k\":\"k\"},{\"t\":29.03,\"k\":\"d\"},{\"t\":29.08,\"k\":\"j\"},{\"t\":29.18,\"k\":\"f\"},{\"t\":29.296,\"k\":\"j\"},{\"t\":29.414,\"k\":\"d\"},{\"t\":29.53,\"k\":\"k\"},{\"t\":29.629,\"k\":\"fj\"},{\"t\":29.863,\"k\":\"kd\"},{\"t\":30.129,\"k\":\"jf\"},{\"t\":30.313,\"k\":\"kd\"},{\"t\":30.463,\"k\":\"jf\"},{\"t\":30.646,\"k\":\"k\"},{\"t\":30.713,\"k\":\"d\"},{\"t\":30.813,\"k\":\"jf\"},{\"t\":30.962,\"k\":\"k\"},{\"t\":31.079,\"k\":\"j\"},{\"t\":31.18,\"k\":\"f\"},{\"t\":31.313,\"k\":\"d\"},{\"t\":31.428,\"k\":\"f\"},{\"t\":31.563,\"k\":\"j\"},{\"t\":31.679,\"k\":\"k\"},{\"t\":31.73,\"k\":\"d\"},{\"t\":31.879,\"k\":\"f\"},{\"t\":32.063,\"k\":\"kd\"},{\"t\":32.246,\"k\":\"jf\"},{\"t\":32.413,\"k\":\"k\"},{\"t\":32.48,\"k\":\"d\"},{\"t\":32.713,\"k\":\"j\"},{\"t\":32.829,\"k\":\"f\"},{\"t\":32.929,\"k\":\"k\"},{\"t\":33.046,\"k\":\"j\"},{\"t\":33.179,\"k\":\"d\"},{\"t\":33.329,\"k\":\"f\"},{\"t\":33.463,\"k\":\"j\"},{\"t\":33.613,\"k\":\"k\"},{\"t\":33.729,\"k\":\"d\"},{\"t\":33.863,\"k\":\"k\"},{\"t\":34.029,\"k\":\"k\"},{\"t\":34.147,\"k\":\"d\"},{\"t\":34.296,\"k\":\"d\"},{\"t\":34.48,\"k\":\"f\"},{\"t\":34.646,\"k\":\"d\"},{\"t\":34.779,\"k\":\"f\"},{\"t\":34.946,\"k\":\"j\"},{\"t\":35.029,\"k\":\"d\"},{\"t\":35.129,\"k\":\"kf\"},{\"t\":35.396,\"k\":\"jf\"},{\"t\":35.679,\"k\":\"kd\"},{\"t\":35.846,\"k\":\"j\"},{\"t\":35.963,\"k\":\"f\"},{\"t\":36.096,\"k\":\"k\"},{\"t\":36.229,\"k\":\"d\"},{\"t\":36.379,\"k\":\"j\"},{\"t\":36.561,\"k\":\"k\"},{\"t\":36.696,\"k\":\"d\"},{\"t\":36.829,\"k\":\"f\"},{\"t\":36.962,\"k\":\"j\"},{\"t\":37.112,\"k\":\"k\"},{\"t\":37.23,\"k\":\"d\"},{\"t\":37.362,\"k\":\"f\"},{\"t\":37.565,\"k\":\"d\"},{\"t\":37.678,\"k\":\"f\"},{\"t\":37.829,\"k\":\"j\"},{\"t\":37.981,\"k\":\"k\"},{\"t\":38.113,\"k\":\"f\"},{\"t\":38.229,\"k\":\"k\"},{\"t\":38.429,\"k\":\"j\"},{\"t\":38.596,\"k\":\"j\"},{\"t\":38.745,\"k\":\"f\"},{\"t\":38.913,\"k\":\"d\"},{\"t\":38.995,\"k\":\"k\"},{\"t\":39.194,\"k\":\"f\"},{\"t\":39.346,\"k\":\"j\"},{\"t\":39.479,\"k\":\"d\"},{\"t\":39.629,\"k\":\"k\"},{\"t\":39.762,\"k\":\"f\"},{\"t\":39.862,\"k\":\"j\"},{\"t\":40.012,\"k\":\"kd\"},{\"t\":40.197,\"k\":\"f\"},{\"t\":40.246,\"k\":\"j\"},{\"t\":40.395,\"k\":\"kd\"},{\"t\":40.562,\"k\":\"j\"},{\"t\":40.679,\"k\":\"f\"},{\"t\":40.929,\"k\":\"k\"},{\"t\":41.046,\"k\":\"d\"},{\"t\":41.129,\"k\":\"j\"},{\"t\":41.229,\"k\":\"f\"},{\"t\":41.329,\"k\":\"k\"},{\"t\":41.479,\"k\":\"k\"},{\"t\":41.596,\"k\":\"d\"},{\"t\":41.73,\"k\":\"f\"},{\"t\":41.896,\"k\":\"j\"},{\"t\":41.979,\"k\":\"d\"},{\"t\":42.128,\"k\":\"f\"},{\"t\":42.262,\"k\":\"j\"},{\"t\":42.429,\"k\":\"k\"},{\"t\":42.548,\"k\":\"d\"},{\"t\":42.696,\"k\":\"j\"},{\"t\":42.862,\"k\":\"f\"},{\"t\":42.978,\"k\":\"k\"},{\"t\":43.128,\"k\":\"d\"},{\"t\":43.263,\"k\":\"j\"},{\"t\":43.396,\"k\":\"j\"},{\"t\":43.528,\"k\":\"d\"},{\"t\":43.679,\"k\":\"f\"},{\"t\":43.83,\"k\":\"k\"},{\"t\":43.996,\"k\":\"j\"},{\"t\":44.161,\"k\":\"d\"},{\"t\":44.328,\"k\":\"f\"},{\"t\":44.48,\"k\":\"k\"},{\"t\":44.629,\"k\":\"k\"},{\"t\":44.779,\"k\":\"d\"},{\"t\":44.942,\"k\":\"f\"},{\"t\":45.162,\"k\":\"d\"},{\"t\":45.296,\"k\":\"f\"},{\"t\":45.451,\"k\":\"j\"},{\"t\":45.613,\"k\":\"j\"},{\"t\":45.712,\"k\":\"f\"},{\"t\":45.796,\"k\":\"j\"},{\"t\":45.895,\"k\":\"f\"},{\"t\":45.964,\"k\":\"j\"},{\"t\":46.096,\"k\":\"fk\"},{\"t\":46.261,\"k\":\"d\"},{\"t\":46.378,\"k\":\"j\"},{\"t\":46.479,\"k\":\"f\"},{\"t\":46.612,\"k\":\"k\"},{\"t\":46.728,\"k\":\"d\"},{\"t\":46.861,\"k\":\"j\"},{\"t\":47.011,\"k\":\"k\"},{\"t\":47.111,\"k\":\"f\"},{\"t\":47.228,\"k\":\"j\"},{\"t\":47.344,\"k\":\"d\"},{\"t\":47.445,\"k\":\"k\"},{\"t\":47.647,\"k\":\"k\"},{\"t\":47.778,\"k\":\"kd\"},{\"t\":48.029,\"k\":\"j\"},{\"t\":48.145,\"k\":\"f\"},{\"t\":48.229,\"k\":\"k\"},{\"t\":48.362,\"k\":\"d\"},{\"t\":48.446,\"k\":\"j\"},{\"t\":48.579,\"k\":\"f\"},{\"t\":48.678,\"k\":\"k\"},{\"t\":48.811,\"k\":\"d\"},{\"t\":48.944,\"k\":\"j\"},{\"t\":49.061,\"k\":\"f\"},{\"t\":49.161,\"k\":\"k\"},{\"t\":49.278,\"k\":\"d\"},{\"t\":49.379,\"k\":\"j\"},{\"t\":49.478,\"k\":\"f\"},{\"t\":49.577,\"k\":\"k\"},{\"t\":49.695,\"k\":\"d\"},{\"t\":49.844,\"k\":\"j\"},{\"t\":49.962,\"k\":\"j\"},{\"t\":50.095,\"k\":\"d\"},{\"t\":50.278,\"k\":\"f\"},{\"t\":50.411,\"k\":\"j\"},{\"t\":50.595,\"k\":\"d\"},{\"t\":50.728,\"k\":\"k\"},{\"t\":50.878,\"k\":\"f\"},{\"t\":50.979,\"k\":\"j\"},{\"t\":51.111,\"k\":\"f\"},{\"t\":51.178,\"k\":\"j\"},{\"t\":51.292,\"k\":\"f\"},{\"t\":51.374,\"k\":\"j\"},{\"t\":51.495,\"k\":\"f\"},{\"t\":51.612,\"k\":\"k\"},{\"t\":51.679,\"k\":\"d\"},{\"t\":51.792,\"k\":\"j\"},{\"t\":51.909,\"k\":\"f\"},{\"t\":51.978,\"k\":\"k\"},{\"t\":52.095,\"k\":\"d\"},{\"t\":52.246,\"k\":\"k\"},{\"t\":52.395,\"k\":\"k\"},{\"t\":52.479,\"k\":\"d\"},{\"t\":52.595,\"k\":\"j\"},{\"t\":52.778,\"k\":\"j\"},{\"t\":52.878,\"k\":\"d\"},{\"t\":53.028,\"k\":\"d\"},{\"t\":53.128,\"k\":\"f\"},{\"t\":53.261,\"k\":\"j\"},{\"t\":53.444,\"k\":\"k\"},{\"t\":53.627,\"k\":\"jd\"},{\"t\":53.845,\"k\":\"f\"},{\"t\":53.978,\"k\":\"k\"},{\"t\":54.145,\"k\":\"d\"},{\"t\":54.21,\"k\":\"j\"},{\"t\":54.394,\"k\":\"f\"},{\"t\":54.478,\"k\":\"k\"},{\"t\":54.644,\"k\":\"d\"},{\"t\":54.728,\"k\":\"j\"},{\"t\":54.878,\"k\":\"f\"},{\"t\":54.961,\"k\":\"k\"},{\"t\":55.094,\"k\":\"d\"},{\"t\":55.196,\"k\":\"j\"},{\"t\":55.345,\"k\":\"j\"},{\"t\":55.494,\"k\":\"f\"},{\"t\":55.644,\"k\":\"k\"},{\"t\":55.778,\"k\":\"d\"},{\"t\":55.911,\"k\":\"j\"},{\"t\":56.011,\"k\":\"f\"},{\"t\":56.128,\"k\":\"k\"},{\"t\":56.195,\"k\":\"d\"},{\"t\":56.428,\"k\":\"kd\"},{\"t\":56.627,\"k\":\"j\"},{\"t\":56.744,\"k\":\"f\"},{\"t\":56.844,\"k\":\"k\"},{\"t\":56.928,\"k\":\"d\"},{\"t\":57.06,\"k\":\"j\"},{\"t\":57.228,\"k\":\"j\"},{\"t\":57.378,\"k\":\"jf\"},{\"t\":57.611,\"k\":\"f\"},{\"t\":57.778,\"k\":\"f\"},{\"t\":57.995,\"k\":\"j\"},{\"t\":58.094,\"k\":\"d\"},{\"t\":58.212,\"k\":\"k\"},{\"t\":58.329,\"k\":\"f\"},{\"t\":58.427,\"k\":\"j\"},{\"t\":58.577,\"k\":\"d\"},{\"t\":58.694,\"k\":\"k\"},{\"t\":58.858,\"k\":\"f\"},{\"t\":58.975,\"k\":\"k\"},{\"t\":59.175,\"k\":\"k\"},{\"t\":59.31,\"k\":\"d\"},{\"t\":59.427,\"k\":\"j\"},{\"t\":59.527,\"k\":\"f\"},{\"t\":59.644,\"k\":\"k\"},{\"t\":59.86,\"k\":\"d\"},{\"t\":59.961,\"k\":\"j\"},{\"t\":60.061,\"k\":\"f\"},{\"t\":60.16,\"k\":\"k\"},{\"t\":60.277,\"k\":\"d\"},{\"t\":60.46,\"k\":\"j\"},{\"t\":60.61,\"k\":\"d\"},{\"t\":60.761,\"k\":\"f\"},{\"t\":60.894,\"k\":\"j\"},{\"t\":61.044,\"k\":\"k\"},{\"t\":61.194,\"k\":\"k\"},{\"t\":61.344,\"k\":\"f\"},{\"t\":61.478,\"k\":\"j\"},{\"t\":61.611,\"k\":\"f\"},{\"t\":61.71,\"k\":\"k\"},{\"t\":61.893,\"k\":\"j\"},{\"t\":62.011,\"k\":\"d\"},{\"t\":62.16,\"k\":\"f\"},{\"t\":62.294,\"k\":\"j\"},{\"t\":62.461,\"k\":\"k\"},{\"t\":62.529,\"k\":\"d\"},{\"t\":62.678,\"k\":\"f\"},{\"t\":62.76,\"k\":\"j\"},{\"t\":62.911,\"k\":\"k\"},{\"t\":63.027,\"k\":\"dj\"},{\"t\":63.21,\"k\":\"f\"},{\"t\":63.327,\"k\":\"k\"},{\"t\":63.477,\"k\":\"j\"},{\"t\":63.61,\"k\":\"f\"},{\"t\":63.76,\"k\":\"d\"},{\"t\":63.91,\"k\":\"f\"},{\"t\":64.04,\"k\":\"j\"},{\"t\":64.191,\"k\":\"k\"},{\"t\":64.278,\"k\":\"j\"},{\"t\":64.445,\"k\":\"f\"},{\"t\":64.627,\"k\":\"d\"},{\"t\":64.76,\"k\":\"f\"},{\"t\":64.91,\"k\":\"j\"},{\"t\":65.077,\"k\":\"k\"},{\"t\":65.21,\"k\":\"j\"},{\"t\":65.374,\"k\":\"k\"},{\"t\":65.493,\"k\":\"j\"},{\"t\":65.627,\"k\":\"f\"},{\"t\":65.777,\"k\":\"d\"},{\"t\":65.943,\"k\":\"f\"},{\"t\":66.127,\"k\":\"j\"},{\"t\":66.293,\"k\":\"k\"},{\"t\":66.477,\"k\":\"d\"},{\"t\":66.611,\"k\":\"f\"},{\"t\":66.761,\"k\":\"j\"},{\"t\":66.943,\"k\":\"k\"},{\"t\":67.061,\"k\":\"j\"},{\"t\":67.226,\"k\":\"f\"},{\"t\":67.36,\"k\":\"d\"},{\"t\":67.493,\"k\":\"f\"},{\"t\":67.644,\"k\":\"j\"},{\"t\":67.793,\"k\":\"k\"},{\"t\":67.91,\"k\":\"j\"},{\"t\":68.059,\"k\":\"f\"},{\"t\":68.209,\"k\":\"d\"},{\"t\":68.344,\"k\":\"f\"},{\"t\":68.494,\"k\":\"j\"},{\"t\":68.644,\"k\":\"k\"},{\"t\":68.76,\"k\":\"j\"},{\"t\":68.961,\"k\":\"f\"},{\"t\":69.126,\"k\":\"d\"},{\"t\":69.277,\"k\":\"f\"},{\"t\":69.426,\"k\":\"j\"},{\"t\":69.591,\"k\":\"k\"},{\"t\":69.743,\"k\":\"d\"},{\"t\":69.86,\"k\":\"f\"},{\"t\":69.993,\"k\":\"j\"},{\"t\":70.143,\"k\":\"k\"},{\"t\":70.259,\"k\":\"d\"},{\"t\":70.393,\"k\":\"f\"},{\"t\":70.509,\"k\":\"j\"},{\"t\":70.659,\"k\":\"k\"},{\"t\":70.726,\"k\":\"d\"},{\"t\":70.86,\"k\":\"f\"},{\"t\":70.977,\"k\":\"j\"},{\"t\":71.124,\"k\":\"d\"},{\"t\":71.243,\"k\":\"f\"},{\"t\":71.343,\"k\":\"j\"},{\"t\":71.476,\"k\":\"d\"},{\"t\":71.577,\"k\":\"f\"},{\"t\":71.759,\"k\":\"d\"},{\"t\":71.859,\"k\":\"f\"},{\"t\":72.009,\"k\":\"j\"},{\"t\":72.159,\"k\":\"d\"},{\"t\":72.293,\"k\":\"f\"},{\"t\":72.377,\"k\":\"j\"},{\"t\":72.543,\"k\":\"d\"},{\"t\":72.677,\"k\":\"j\"},{\"t\":72.742,\"k\":\"f\"},{\"t\":72.942,\"k\":\"d\"},{\"t\":73.109,\"k\":\"j\"},{\"t\":73.159,\"k\":\"f\"},{\"t\":73.36,\"k\":\"kd\"},{\"t\":73.51,\"k\":\"j\"},{\"t\":73.576,\"k\":\"f\"},{\"t\":73.71,\"k\":\"k\"},{\"t\":73.825,\"k\":\"d\"},{\"t\":73.942,\"k\":\"j\"},{\"t\":74.059,\"k\":\"f\"},{\"t\":74.159,\"k\":\"k\"},{\"t\":74.259,\"k\":\"d\"},{\"t\":74.342,\"k\":\"j\"},{\"t\":74.459,\"k\":\"f\"},{\"t\":74.559,\"k\":\"k\"},{\"t\":74.659,\"k\":\"jd\"},{\"t\":74.843,\"k\":\"f\"},{\"t\":74.91,\"k\":\"k\"},{\"t\":75.026,\"k\":\"j\"},{\"t\":75.093,\"k\":\"d\"},{\"t\":75.193,\"k\":\"f\"},{\"t\":75.276,\"k\":\"k\"},{\"t\":75.376,\"k\":\"j\"},{\"t\":75.476,\"k\":\"d\"},{\"t\":75.608,\"k\":\"k\"},{\"t\":75.675,\"k\":\"j\"},{\"t\":75.775,\"k\":\"f\"},{\"t\":75.925,\"k\":\"k\"},{\"t\":76.009,\"k\":\"d\"},{\"t\":76.159,\"k\":\"j\"},{\"t\":76.293,\"k\":\"f\"},{\"t\":76.409,\"k\":\"k\"},{\"t\":76.509,\"k\":\"d\"},{\"t\":76.592,\"k\":\"j\"},{\"t\":76.692,\"k\":\"f\"},{\"t\":76.809,\"k\":\"k\"},{\"t\":76.893,\"k\":\"d\"},{\"t\":76.993,\"k\":\"j\"},{\"t\":77.076,\"k\":\"f\"},{\"t\":77.209,\"k\":\"kd\",\"h\":{\"k\":112.78907419957488,\"d\":112.7390742472586}},{\"t\":82.443,\"k\":\"fj\"},{\"t\":82.759,\"k\":\"fj\"},{\"t\":83.042,\"k\":\"fj\"},{\"t\":83.359,\"k\":\"fj\"},{\"t\":83.659,\"k\":\"fj\"},{\"t\":84.009,\"k\":\"fj\"},{\"t\":84.325,\"k\":\"jf\"},{\"t\":84.642,\"k\":\"jf\"},{\"t\":84.925,\"k\":\"jf\"},{\"t\":85.305,\"k\":\"jf\"},{\"t\":85.659,\"k\":\"fj\"},{\"t\":85.992,\"k\":\"fj\"},{\"t\":86.292,\"k\":\"jf\"},{\"t\":86.608,\"k\":\"jf\"},{\"t\":86.908,\"k\":\"jf\"},{\"t\":87.208,\"k\":\"jf\"},{\"t\":87.374,\"k\":\"jf\"},{\"t\":87.54,\"k\":\"jf\"},{\"t\":87.842,\"k\":\"jf\"},{\"t\":88.175,\"k\":\"fj\"},{\"t\":88.525,\"k\":\"fj\"},{\"t\":88.858,\"k\":\"fj\"},{\"t\":89.208,\"k\":\"jf\"},{\"t\":89.509,\"k\":\"jf\"},{\"t\":89.825,\"k\":\"jf\"},{\"t\":90.158,\"k\":\"fj\"},{\"t\":90.491,\"k\":\"jf\"},{\"t\":90.808,\"k\":\"fj\"},{\"t\":91.141,\"k\":\"jf\"},{\"t\":91.458,\"k\":\"jf\"},{\"t\":91.774,\"k\":\"fj\"},{\"t\":92.074,\"k\":\"jf\"},{\"t\":92.407,\"k\":\"fj\"},{\"t\":92.658,\"k\":\"j\"},{\"t\":92.774,\"k\":\"f\"},{\"t\":92.874,\"k\":\"j\"},{\"t\":93.008,\"k\":\"f\"},{\"t\":93.124,\"k\":\"j\"},{\"t\":93.241,\"k\":\"f\"},{\"t\":93.391,\"k\":\"j\"},{\"t\":93.624,\"k\":\"f\"},{\"t\":93.724,\"k\":\"j\"},{\"t\":93.859,\"k\":\"f\"},{\"t\":93.975,\"k\":\"j\"},{\"t\":94.174,\"k\":\"f\"},{\"t\":94.257,\"k\":\"j\"},{\"t\":94.375,\"k\":\"f\"},{\"t\":94.475,\"k\":\"j\"},{\"t\":94.592,\"k\":\"f\"},{\"t\":94.725,\"k\":\"j\"},{\"t\":94.941,\"k\":\"j\"},{\"t\":95.074,\"k\":\"f\"},{\"t\":95.224,\"k\":\"j\"},{\"t\":95.391,\"k\":\"f\"},{\"t\":95.507,\"k\":\"j\"},{\"t\":95.657,\"k\":\"j\"},{\"t\":95.757,\"k\":\"f\"},{\"t\":95.94,\"k\":\"f\"},{\"t\":96.107,\"k\":\"f\"},{\"t\":96.261,\"k\":\"j\"},{\"t\":96.374,\"k\":\"f\"},{\"t\":96.524,\"k\":\"j\"},{\"t\":96.674,\"k\":\"j\"},{\"t\":96.907,\"k\":\"f\"},{\"t\":97.057,\"k\":\"j\"},{\"t\":97.204,\"k\":\"f\"},{\"t\":97.325,\"k\":\"j\"},{\"t\":97.475,\"k\":\"f\"},{\"t\":97.592,\"k\":\"j\"},{\"t\":97.891,\"k\":\"j\"},{\"t\":98.058,\"k\":\"f\"},{\"t\":98.157,\"k\":\"j\"},{\"t\":98.275,\"k\":\"f\"},{\"t\":98.407,\"k\":\"j\"},{\"t\":98.523,\"k\":\"f\"},{\"t\":98.775,\"k\":\"j\"},{\"t\":98.957,\"k\":\"f\"},{\"t\":99.14,\"k\":\"f\"},{\"t\":99.325,\"k\":\"j\"},{\"t\":99.491,\"k\":\"j\"},{\"t\":99.624,\"k\":\"f\"},{\"t\":99.773,\"k\":\"f\"},{\"t\":99.89,\"k\":\"j\"},{\"t\":100.023,\"k\":\"j\"},{\"t\":100.173,\"k\":\"f\"},{\"t\":100.323,\"k\":\"f\"},{\"t\":100.54,\"k\":\"j\"},{\"t\":100.673,\"k\":\"j\"},{\"t\":100.807,\"k\":\"f\"},{\"t\":100.941,\"k\":\"f\"},{\"t\":101.058,\"k\":\"j\"},{\"t\":101.174,\"k\":\"j\"},{\"t\":101.257,\"k\":\"f\"},{\"t\":101.407,\"k\":\"j\"},{\"t\":101.54,\"k\":\"f\"},{\"t\":101.607,\"k\":\"j\"},{\"t\":101.724,\"k\":\"f\"},{\"t\":101.874,\"k\":\"j\"},{\"t\":102.008,\"k\":\"f\"},{\"t\":102.14,\"k\":\"j\"},{\"t\":102.256,\"k\":\"f\"},{\"t\":102.373,\"k\":\"j\"},{\"t\":102.473,\"k\":\"f\"},{\"t\":102.606,\"k\":\"j\"},{\"t\":102.706,\"k\":\"f\"},{\"t\":102.79,\"k\":\"j\"},{\"t\":102.906,\"k\":\"f\"},{\"t\":103.006,\"k\":\"j\"},{\"t\":103.123,\"k\":\"f\"},{\"t\":103.223,\"k\":\"j\"},{\"t\":103.323,\"k\":\"f\"},{\"t\":103.436,\"k\":\"j\"},{\"t\":103.52,\"k\":\"f\"},{\"t\":103.639,\"k\":\"j\"},{\"t\":103.723,\"k\":\"f\"},{\"t\":103.857,\"k\":\"j\"},{\"t\":103.957,\"k\":\"f\"},{\"t\":104.074,\"k\":\"j\"},{\"t\":104.174,\"k\":\"f\"},{\"t\":104.274,\"k\":\"j\"},{\"t\":104.374,\"k\":\"f\"},{\"t\":104.49,\"k\":\"j\"},{\"t\":104.607,\"k\":\"f\"},{\"t\":104.707,\"k\":\"j\"},{\"t\":104.811,\"k\":\"f\"},{\"t\":104.924,\"k\":\"j\"},{\"t\":105.04,\"k\":\"f\"},{\"t\":105.14,\"k\":\"j\"},{\"t\":105.256,\"k\":\"f\"},{\"t\":105.374,\"k\":\"j\"},{\"t\":105.474,\"k\":\"f\"},{\"t\":105.589,\"k\":\"j\"},{\"t\":105.677,\"k\":\"f\"},{\"t\":105.789,\"k\":\"j\"},{\"t\":105.906,\"k\":\"f\"},{\"t\":106.022,\"k\":\"j\"},{\"t\":106.14,\"k\":\"f\"},{\"t\":106.223,\"k\":\"j\"},{\"t\":106.356,\"k\":\"f\"},{\"t\":106.456,\"k\":\"j\"},{\"t\":106.556,\"k\":\"f\"},{\"t\":106.657,\"k\":\"j\"},{\"t\":106.773,\"k\":\"f\"},{\"t\":106.873,\"k\":\"j\"},{\"t\":106.99,\"k\":\"f\"},{\"t\":107.089,\"k\":\"j\"},{\"t\":107.189,\"k\":\"f\"},{\"t\":107.307,\"k\":\"j\"},{\"t\":107.423,\"k\":\"f\"},{\"t\":107.523,\"k\":\"j\"},{\"t\":107.657,\"k\":\"f\"},{\"t\":107.723,\"k\":\"j\"},{\"t\":107.922,\"k\":\"fj\"},{\"t\":108.239,\"k\":\"jf\",\"h\":{\"j\":112.75507427968353,\"f\":112.7720742396292}},{\"t\":112.906,\"k\":\"fkd\"},{\"t\":112.956,\"k\":\"j\"},{\"t\":113.073,\"k\":\"fj\"},{\"t\":113.123,\"k\":\"kd\"},{\"t\":113.306,\"k\":\"j\"},{\"t\":113.406,\"k\":\"f\"},{\"t\":113.506,\"k\":\"k\"},{\"t\":113.556,\"k\":\"d\"},{\"t\":113.656,\"k\":\"j\"},{\"t\":113.789,\"k\":\"f\"},{\"t\":113.923,\"k\":\"kd\"},{\"t\":114.073,\"k\":\"j\"},{\"t\":114.206,\"k\":\"f\"},{\"t\":114.289,\"k\":\"kd\"},{\"t\":114.406,\"k\":\"j\"},{\"t\":114.573,\"k\":\"jf\"},{\"t\":114.739,\"k\":\"j\"},{\"t\":114.822,\"k\":\"f\"},{\"t\":114.906,\"k\":\"j\"},{\"t\":115.006,\"k\":\"f\"},{\"t\":115.089,\"k\":\"j\"},{\"t\":115.206,\"k\":\"f\"},{\"t\":115.289,\"k\":\"j\"},{\"t\":115.389,\"k\":\"f\"},{\"t\":115.572,\"k\":\"f\"},{\"t\":115.656,\"k\":\"k\"},{\"t\":115.706,\"k\":\"d\"},{\"t\":115.806,\"k\":\"j\"},{\"t\":115.872,\"k\":\"f\"},{\"t\":116.022,\"k\":\"kd\"},{\"t\":116.206,\"k\":\"dk\"},{\"t\":116.373,\"k\":\"jf\"},{\"t\":116.539,\"k\":\"k\"},{\"t\":116.589,\"k\":\"d\"},{\"t\":116.656,\"k\":\"j\"},{\"t\":116.772,\"k\":\"f\"},{\"t\":116.839,\"k\":\"k\"},{\"t\":116.906,\"k\":\"d\"},{\"t\":117.022,\"k\":\"j\"},{\"t\":117.172,\"k\":\"f\"},{\"t\":117.272,\"k\":\"j\"},{\"t\":117.372,\"k\":\"f\"},{\"t\":117.439,\"k\":\"j\"},{\"t\":117.572,\"k\":\"f\"},{\"t\":117.622,\"k\":\"j\"},{\"t\":117.756,\"k\":\"f\"},{\"t\":117.822,\"k\":\"j\"},{\"t\":117.939,\"k\":\"f\"},{\"t\":118.022,\"k\":\"k\"},{\"t\":118.089,\"k\":\"d\"},{\"t\":118.185,\"k\":\"j\"},{\"t\":118.318,\"k\":\"f\"},{\"t\":118.406,\"k\":\"k\"},{\"t\":118.456,\"k\":\"d\"},{\"t\":118.623,\"k\":\"kd\"},{\"t\":118.79,\"k\":\"kd\"},{\"t\":118.955,\"k\":\"j\"},{\"t\":119.022,\"k\":\"f\"},{\"t\":119.139,\"k\":\"k\"},{\"t\":119.205,\"k\":\"d\"},{\"t\":119.289,\"k\":\"j\"},{\"t\":119.389,\"k\":\"f\"},{\"t\":119.489,\"k\":\"k\"},{\"t\":119.539,\"k\":\"d\"},{\"t\":119.69,\"k\":\"k\"},{\"t\":119.79,\"k\":\"d\"},{\"t\":119.872,\"k\":\"k\"},{\"t\":119.972,\"k\":\"d\"},{\"t\":120.055,\"k\":\"k\"},{\"t\":120.155,\"k\":\"d\"},{\"t\":120.239,\"k\":\"k\"},{\"t\":120.372,\"k\":\"d\"},{\"t\":120.439,\"k\":\"k\"},{\"t\":120.555,\"k\":\"d\"},{\"t\":120.64,\"k\":\"j\"},{\"t\":120.739,\"k\":\"f\"},{\"t\":120.823,\"k\":\"k\"},{\"t\":120.889,\"k\":\"d\"},{\"t\":120.955,\"k\":\"j\"},{\"t\":121.055,\"k\":\"f\"},{\"t\":121.172,\"k\":\"j\"},{\"t\":121.222,\"k\":\"f\"},{\"t\":121.338,\"k\":\"j\"},{\"t\":121.39,\"k\":\"f\"},{\"t\":121.522,\"k\":\"k\"},{\"t\":121.572,\"k\":\"d\"},{\"t\":121.672,\"k\":\"j\"},{\"t\":121.788,\"k\":\"f\"},{\"t\":121.855,\"k\":\"k\"},{\"t\":121.939,\"k\":\"dj\"},{\"t\":122.073,\"k\":\"f\"},{\"t\":122.172,\"k\":\"k\"},{\"t\":122.272,\"k\":\"jd\"},{\"t\":122.422,\"k\":\"f\"},{\"t\":122.488,\"k\":\"k\"},{\"t\":122.588,\"k\":\"jd\"},{\"t\":122.688,\"k\":\"f\"},{\"t\":122.772,\"k\":\"k\"},{\"t\":122.855,\"k\":\"jd\"},{\"t\":123.089,\"k\":\"k\"},{\"t\":123.173,\"k\":\"dj\"},{\"t\":123.356,\"k\":\"kf\"},{\"t\":123.455,\"k\":\"j\"},{\"t\":123.555,\"k\":\"d\"},{\"t\":123.688,\"k\":\"j\"},{\"t\":123.788,\"k\":\"f\"},{\"t\":123.871,\"k\":\"j\"},{\"t\":123.971,\"k\":\"f\"},{\"t\":124.038,\"k\":\"k\"},{\"t\":124.105,\"k\":\"d\"},{\"t\":124.188,\"k\":\"j\"},{\"t\":124.355,\"k\":\"kf\"},{\"t\":124.471,\"k\":\"jd\"},{\"t\":124.671,\"k\":\"f\"},{\"t\":124.738,\"k\":\"j\"},{\"t\":124.872,\"k\":\"k\"},{\"t\":124.972,\"k\":\"d\"},{\"t\":125.139,\"k\":\"k\"},{\"t\":125.306,\"k\":\"jf\"},{\"t\":125.455,\"k\":\"j\"},{\"t\":125.622,\"k\":\"j\"},{\"t\":125.789,\"k\":\"k\"},{\"t\":125.918,\"k\":\"j\"},{\"t\":126.035,\"k\":\"f\"},{\"t\":126.118,\"k\":\"k\"},{\"t\":126.169,\"k\":\"d\"},{\"t\":126.319,\"k\":\"fj\"},{\"t\":126.505,\"k\":\"k\"},{\"t\":126.571,\"k\":\"d\"},{\"t\":126.721,\"k\":\"f\"},{\"t\":126.821,\"k\":\"j\"},{\"t\":126.955,\"k\":\"k\"},{\"t\":127.055,\"k\":\"jd\"},{\"t\":127.189,\"k\":\"f\"},{\"t\":127.272,\"k\":\"k\"},{\"t\":127.388,\"k\":\"j\"},{\"t\":127.504,\"k\":\"dk\"},{\"t\":127.638,\"k\":\"j\"},{\"t\":127.754,\"k\":\"f\"},{\"t\":127.854,\"k\":\"k\"},{\"t\":127.938,\"k\":\"jd\"},{\"t\":128.054,\"k\":\"f\"},{\"t\":128.154,\"k\":\"k\"},{\"t\":128.254,\"k\":\"j\"},{\"t\":128.371,\"k\":\"f\"},{\"t\":128.488,\"k\":\"k\"},{\"t\":128.571,\"k\":\"d\"},{\"t\":128.804,\"k\":\"fj\"},{\"t\":129.005,\"k\":\"d\"},{\"t\":129.105,\"k\":\"kf\"},{\"t\":129.271,\"k\":\"j\"},{\"t\":129.388,\"k\":\"d\"},{\"t\":129.455,\"k\":\"k\"},{\"t\":129.588,\"k\":\"f\"},{\"t\":129.687,\"k\":\"j\"},{\"t\":129.804,\"k\":\"d\"},{\"t\":129.905,\"k\":\"kf\"},{\"t\":130.055,\"k\":\"j\"},{\"t\":130.172,\"k\":\"d\"},{\"t\":130.255,\"k\":\"k\"},{\"t\":130.405,\"k\":\"j\"},{\"t\":130.555,\"k\":\"fk\"},{\"t\":130.654,\"k\":\"j\"},{\"t\":130.771,\"k\":\"d\"},{\"t\":130.837,\"k\":\"k\"},{\"t\":130.937,\"k\":\"jf\"},{\"t\":131.104,\"k\":\"kd\"},{\"t\":131.288,\"k\":\"jf\"},{\"t\":131.534,\"k\":\"kd\"},{\"t\":132.204,\"k\":\"jf\"},{\"t\":132.888,\"k\":\"kfd\"},{\"t\":132.938,\"k\":\"j\"},{\"t\":133.071,\"k\":\"dfkj\"},{\"t\":133.255,\"k\":\"kjf\"},{\"t\":133.305,\"k\":\"d\"},{\"t\":133.455,\"k\":\"kfd\"},{\"t\":133.504,\"k\":\"j\"},{\"t\":133.638,\"k\":\"dkf\"},{\"t\":133.688,\"k\":\"j\"},{\"t\":133.821,\"k\":\"jf\"},{\"t\":133.988,\"k\":\"dk\"},{\"t\":134.121,\"k\":\"jf\"},{\"t\":134.288,\"k\":\"k\"},{\"t\":134.388,\"k\":\"d\"},{\"t\":134.52,\"k\":\"j\"},{\"t\":134.637,\"k\":\"f\"},{\"t\":134.737,\"k\":\"k\"},{\"t\":134.854,\"k\":\"j\"},{\"t\":134.953,\"k\":\"d\"},{\"t\":135.087,\"k\":\"f\"},{\"t\":135.187,\"k\":\"j\"},{\"t\":135.337,\"k\":\"k\"},{\"t\":135.487,\"k\":\"d\"},{\"t\":135.603,\"k\":\"k\"},{\"t\":135.738,\"k\":\"fj\"},{\"t\":135.902,\"k\":\"k\"},{\"t\":136.002,\"k\":\"d\"},{\"t\":136.086,\"k\":\"j\"},{\"t\":136.271,\"k\":\"k\"},{\"t\":136.405,\"k\":\"j\"},{\"t\":136.505,\"k\":\"d\"},{\"t\":136.638,\"k\":\"f\"},{\"t\":136.737,\"k\":\"j\"},{\"t\":136.871,\"k\":\"j\"},{\"t\":136.986,\"k\":\"f\"},{\"t\":137.137,\"k\":\"j\"},{\"t\":137.271,\"k\":\"kd\"},{\"t\":137.453,\"k\":\"j\"},{\"t\":137.687,\"k\":\"f\"},{\"t\":137.787,\"k\":\"k\"},{\"t\":137.87,\"k\":\"d\"},{\"t\":137.954,\"k\":\"j\"},{\"t\":138.054,\"k\":\"f\"},{\"t\":138.138,\"k\":\"k\"},{\"t\":138.304,\"k\":\"d\"},{\"t\":138.421,\"k\":\"j\"},{\"t\":138.537,\"k\":\"f\"},{\"t\":138.621,\"k\":\"k\"},{\"t\":138.771,\"k\":\"d\"},{\"t\":138.987,\"k\":\"f\"},{\"t\":139.104,\"k\":\"j\"},{\"t\":139.221,\"k\":\"d\"},{\"t\":139.287,\"k\":\"k\"},{\"t\":139.421,\"k\":\"j\"},{\"t\":139.471,\"k\":\"f\"},{\"t\":139.587,\"k\":\"k\"},{\"t\":139.687,\"k\":\"d\"},{\"t\":139.754,\"k\":\"j\"},{\"t\":139.87,\"k\":\"f\"},{\"t\":139.936,\"k\":\"k\"},{\"t\":140.036,\"k\":\"jd\"},{\"t\":140.17,\"k\":\"f\"},{\"t\":140.254,\"k\":\"j\"},{\"t\":140.37,\"k\":\"d\"},{\"t\":140.47,\"k\":\"k\"},{\"t\":140.537,\"k\":\"j\"},{\"t\":140.654,\"k\":\"fk\"},{\"t\":140.787,\"k\":\"jd\"},{\"t\":140.97,\"k\":\"f\"},{\"t\":141.02,\"k\":\"j\"},{\"t\":141.187,\"k\":\"dk\"},{\"t\":141.304,\"k\":\"j\"},{\"t\":141.354,\"k\":\"f\"},{\"t\":141.42,\"k\":\"k\"},{\"t\":141.537,\"k\":\"jd\"},{\"t\":141.72,\"k\":\"jf\"},{\"t\":141.887,\"k\":\"k\"},{\"t\":141.953,\"k\":\"dj\"},{\"t\":142.12,\"k\":\"j\"},{\"t\":142.187,\"k\":\"f\"},{\"t\":142.32,\"k\":\"k\"},{\"t\":142.403,\"k\":\"d\"},{\"t\":142.504,\"k\":\"j\"},{\"t\":142.637,\"k\":\"f\"},{\"t\":142.737,\"k\":\"k\"},{\"t\":142.853,\"k\":\"d\"},{\"t\":142.987,\"k\":\"j\"},{\"t\":143.07,\"k\":\"f\"},{\"t\":143.237,\"k\":\"d\"},{\"t\":143.337,\"k\":\"f\"},{\"t\":143.47,\"k\":\"j\"},{\"t\":143.587,\"k\":\"d\"},{\"t\":143.687,\"k\":\"k\"},{\"t\":143.77,\"k\":\"j\"},{\"t\":143.853,\"k\":\"f\"},{\"t\":143.948,\"k\":\"k\"},{\"t\":144.015,\"k\":\"d\"},{\"t\":144.085,\"k\":\"j\"},{\"t\":144.148,\"k\":\"f\"},{\"t\":144.299,\"k\":\"k\"},{\"t\":144.437,\"k\":\"jf\"},{\"t\":144.653,\"k\":\"d\"},{\"t\":144.837,\"k\":\"j\"},{\"t\":144.987,\"k\":\"f\"},{\"t\":145.103,\"k\":\"k\"},{\"t\":145.203,\"k\":\"d\"},{\"t\":145.353,\"k\":\"j\"},{\"t\":145.503,\"k\":\"f\"},{\"t\":145.637,\"k\":\"k\"},{\"t\":145.77,\"k\":\"j\"},{\"t\":145.953,\"k\":\"d\"},{\"t\":146.17,\"k\":\"j\"},{\"t\":146.286,\"k\":\"f\"},{\"t\":146.453,\"k\":\"k\"},{\"t\":146.753,\"k\":\"d\"},{\"t\":146.886,\"k\":\"j\"},{\"t\":147.021,\"k\":\"f\"},{\"t\":147.154,\"k\":\"k\"},{\"t\":147.37,\"k\":\"d\"},{\"t\":147.52,\"k\":\"j\"},{\"t\":147.67,\"k\":\"f\"},{\"t\":147.786,\"k\":\"k\"},{\"t\":147.937,\"k\":\"d\"},{\"t\":148.037,\"k\":\"j\"},{\"t\":148.17,\"k\":\"f\"},{\"t\":148.253,\"k\":\"k\"},{\"t\":148.32,\"k\":\"d\"},{\"t\":148.369,\"k\":\"j\"},{\"t\":148.519,\"k\":\"k\"},{\"t\":148.586,\"k\":\"j\"},{\"t\":148.803,\"k\":\"f\"},{\"t\":148.936,\"k\":\"d\"},{\"t\":149.086,\"k\":\"jf\"},{\"t\":149.286,\"k\":\"dk\"},{\"t\":149.503,\"k\":\"fj\"},{\"t\":149.781,\"k\":\"kd\"},{\"t\":149.953,\"k\":\"j\"},{\"t\":150.019,\"k\":\"f\"},{\"t\":150.153,\"k\":\"k\"},{\"t\":150.253,\"k\":\"d\"},{\"t\":150.436,\"k\":\"j\"},{\"t\":150.602,\"k\":\"f\"},{\"t\":150.753,\"k\":\"k\"},{\"t\":150.886,\"k\":\"d\"},{\"t\":151.053,\"k\":\"j\"},{\"t\":151.187,\"k\":\"f\"},{\"t\":151.369,\"k\":\"k\"},{\"t\":151.502,\"k\":\"d\"},{\"t\":151.686,\"k\":\"j\"},{\"t\":151.836,\"k\":\"f\"},{\"t\":151.986,\"k\":\"k\"},{\"t\":152.119,\"k\":\"d\"},{\"t\":152.286,\"k\":\"j\"},{\"t\":152.452,\"k\":\"f\"},{\"t\":152.619,\"k\":\"k\"},{\"t\":152.769,\"k\":\"d\"},{\"t\":152.952,\"k\":\"j\"},{\"t\":153.119,\"k\":\"f\"},{\"t\":153.303,\"k\":\"k\"},{\"t\":153.436,\"k\":\"d\"},{\"t\":153.586,\"k\":\"j\"},{\"t\":153.752,\"k\":\"f\"},{\"t\":153.919,\"k\":\"k\"},{\"t\":154.081,\"k\":\"j\"},{\"t\":154.27,\"k\":\"d\"},{\"t\":154.437,\"k\":\"f\"},{\"t\":154.669,\"k\":\"j\"},{\"t\":154.802,\"k\":\"d\"},{\"t\":154.985,\"k\":\"k\"},{\"t\":155.152,\"k\":\"f\"},{\"t\":155.335,\"k\":\"j\"},{\"t\":155.519,\"k\":\"d\"},{\"t\":155.702,\"k\":\"k\"},{\"t\":155.885,\"k\":\"f\"},{\"t\":156.002,\"k\":\"j\"},{\"t\":156.152,\"k\":\"d\"},{\"t\":156.336,\"k\":\"f\"},{\"t\":156.553,\"k\":\"j\"},{\"t\":156.736,\"k\":\"d\"},{\"t\":156.886,\"k\":\"f\"},{\"t\":157.019,\"k\":\"j\"},{\"t\":157.152,\"k\":\"k\"},{\"t\":157.253,\"k\":\"d\"},{\"t\":157.303,\"k\":\"j\"},{\"t\":157.436,\"k\":\"f\"},{\"t\":157.552,\"k\":\"k\",\"h\":{\"k\":179.29900407470632}},{\"t\":157.602,\"k\":\"d\",\"h\":{\"d\":179.316004034652}},{\"t\":158.936,\"k\":\"fj\"},{\"t\":161.202,\"k\":\"jf\"},{\"t\":163.952,\"k\":\"fj\"},{\"t\":166.768,\"k\":\"fj\"},{\"t\":167.818,\"k\":\"jf\"},{\"t\":168.418,\"k\":\"fj\"},{\"t\":168.885,\"k\":\"jf\"},{\"t\":169.068,\"k\":\"jf\"},{\"t\":169.251,\"k\":\"j\"},{\"t\":169.351,\"k\":\"f\"},{\"t\":169.468,\"k\":\"j\"},{\"t\":169.585,\"k\":\"f\"},{\"t\":169.685,\"k\":\"j\"},{\"t\":169.801,\"k\":\"f\"},{\"t\":169.885,\"k\":\"j\"},{\"t\":170.018,\"k\":\"f\"},{\"t\":170.101,\"k\":\"j\"},{\"t\":170.218,\"k\":\"f\"},{\"t\":170.334,\"k\":\"j\"},{\"t\":170.418,\"k\":\"f\"},{\"t\":170.551,\"k\":\"j\"},{\"t\":170.651,\"k\":\"f\"},{\"t\":170.748,\"k\":\"j\"},{\"t\":170.848,\"k\":\"f\"},{\"t\":170.965,\"k\":\"j\"},{\"t\":171.067,\"k\":\"f\"},{\"t\":171.184,\"k\":\"j\"},{\"t\":171.284,\"k\":\"f\"},{\"t\":171.384,\"k\":\"j\"},{\"t\":171.451,\"k\":\"f\"},{\"t\":171.617,\"k\":\"j\"},{\"t\":171.784,\"k\":\"fj\"},{\"t\":172.018,\"k\":\"j\"},{\"t\":172.118,\"k\":\"f\"},{\"t\":172.234,\"k\":\"j\"},{\"t\":172.351,\"k\":\"f\"},{\"t\":172.451,\"k\":\"j\"},{\"t\":172.584,\"k\":\"f\"},{\"t\":172.684,\"k\":\"j\"},{\"t\":172.784,\"k\":\"f\"},{\"t\":172.901,\"k\":\"j\"},{\"t\":173.018,\"k\":\"f\"},{\"t\":173.134,\"k\":\"j\"},{\"t\":173.234,\"k\":\"f\"},{\"t\":173.351,\"k\":\"j\"},{\"t\":173.451,\"k\":\"f\"},{\"t\":173.584,\"k\":\"j\"},{\"t\":173.684,\"k\":\"f\"},{\"t\":173.801,\"k\":\"j\"},{\"t\":173.901,\"k\":\"f\"},{\"t\":174.017,\"k\":\"j\"},{\"t\":174.117,\"k\":\"f\"},{\"t\":174.334,\"k\":\"jf\"},{\"t\":174.601,\"k\":\"j\"},{\"t\":174.701,\"k\":\"f\"},{\"t\":174.817,\"k\":\"j\"},{\"t\":174.917,\"k\":\"f\"},{\"t\":175.017,\"k\":\"j\"},{\"t\":175.134,\"k\":\"f\"},{\"t\":175.251,\"k\":\"j\"},{\"t\":175.351,\"k\":\"f\"},{\"t\":175.451,\"k\":\"j\"},{\"t\":175.717,\"k\":\"jf\"},{\"t\":175.918,\"k\":\"j\"},{\"t\":176.017,\"k\":\"f\"},{\"t\":176.134,\"k\":\"j\"},{\"t\":176.234,\"k\":\"f\"},{\"t\":176.334,\"k\":\"j\"},{\"t\":176.451,\"k\":\"f\"},{\"t\":176.55,\"k\":\"j\"},{\"t\":176.7,\"k\":\"f\"},{\"t\":176.75,\"k\":\"j\"},{\"t\":177,\"k\":\"jf\"},{\"t\":177.617,\"k\":\"fj\"},{\"t\":178.234,\"k\":\"jf\"},{\"t\":178.6,\"k\":\"fj\"},{\"t\":178.967,\"k\":\"fj\"},{\"t\":179.267,\"k\":\"fj\"},{\"t\":179.45,\"k\":\"k\"},{\"t\":179.5,\"k\":\"d\"},{\"t\":179.61,\"k\":\"j\"},{\"t\":179.676,\"k\":\"f\"},{\"t\":179.783,\"k\":\"k\"},{\"t\":179.883,\"k\":\"d\"},{\"t\":180.017,\"k\":\"f\"},{\"t\":180.112,\"k\":\"j\"},{\"t\":180.245,\"k\":\"j\"},{\"t\":180.384,\"k\":\"f\"},{\"t\":180.55,\"k\":\"f\"},{\"t\":180.7,\"k\":\"f\"},{\"t\":180.867,\"k\":\"j\"},{\"t\":180.967,\"k\":\"f\"},{\"t\":181.071,\"k\":\"k\"},{\"t\":181.167,\"k\":\"d\"},{\"t\":181.267,\"k\":\"j\"},{\"t\":181.4,\"k\":\"f\"},{\"t\":181.45,\"k\":\"k\"},{\"t\":181.552,\"k\":\"j\"},{\"t\":181.618,\"k\":\"d\"},{\"t\":181.767,\"k\":\"f\"},{\"t\":181.867,\"k\":\"j\"},{\"t\":182.016,\"k\":\"k\"},{\"t\":182.183,\"k\":\"d\"},{\"t\":182.368,\"k\":\"d\"},{\"t\":182.55,\"k\":\"f\"},{\"t\":182.683,\"k\":\"j\"},{\"t\":182.801,\"k\":\"f\"},{\"t\":182.901,\"k\":\"k\"},{\"t\":183.067,\"k\":\"k\"},{\"t\":183.201,\"k\":\"d\"},{\"t\":183.367,\"k\":\"f\"},{\"t\":183.518,\"k\":\"k\"},{\"t\":183.601,\"k\":\"d\"},{\"t\":183.667,\"k\":\"j\"},{\"t\":183.783,\"k\":\"f\"},{\"t\":183.85,\"k\":\"k\"},{\"t\":183.933,\"k\":\"d\"},{\"t\":184.116,\"k\":\"j\"},{\"t\":184.216,\"k\":\"f\"},{\"t\":184.31,\"k\":\"j\"},{\"t\":184.394,\"k\":\"f\"},{\"t\":184.46,\"k\":\"k\"},{\"t\":184.566,\"k\":\"d\"},{\"t\":184.633,\"k\":\"j\"},{\"t\":184.716,\"k\":\"f\"},{\"t\":184.8,\"k\":\"k\"},{\"t\":184.983,\"k\":\"d\"},{\"t\":185.149,\"k\":\"jf\"},{\"t\":185.35,\"k\":\"k\"},{\"t\":185.399,\"k\":\"d\"},{\"t\":185.55,\"k\":\"jf\"},{\"t\":185.7,\"k\":\"k\"},{\"t\":185.8,\"k\":\"d\"},{\"t\":185.934,\"k\":\"j\"},{\"t\":186.034,\"k\":\"f\"},{\"t\":186.149,\"k\":\"k\"},{\"t\":186.266,\"k\":\"d\"},{\"t\":186.383,\"k\":\"j\"},{\"t\":186.483,\"k\":\"f\"},{\"t\":186.584,\"k\":\"k\"},{\"t\":186.7,\"k\":\"d\"},{\"t\":186.817,\"k\":\"j\"},{\"t\":186.934,\"k\":\"f\"},{\"t\":187.034,\"k\":\"k\"},{\"t\":187.134,\"k\":\"d\"},{\"t\":187.267,\"k\":\"j\"},{\"t\":187.358,\"k\":\"f\"},{\"t\":187.425,\"k\":\"k\"},{\"t\":187.525,\"k\":\"d\"},{\"t\":187.65,\"k\":\"j\"},{\"t\":187.75,\"k\":\"f\"},{\"t\":187.834,\"k\":\"k\"},{\"t\":187.933,\"k\":\"d\"},{\"t\":188.049,\"k\":\"j\"},{\"t\":188.166,\"k\":\"k\"},{\"t\":188.332,\"k\":\"d\"},{\"t\":188.466,\"k\":\"f\"},{\"t\":188.617,\"k\":\"d\"},{\"t\":188.733,\"k\":\"f\"},{\"t\":188.883,\"k\":\"f\"},{\"t\":189.017,\"k\":\"d\"},{\"t\":189.15,\"k\":\"jf\"},{\"t\":189.333,\"k\":\"k\"},{\"t\":189.417,\"k\":\"j\"},{\"t\":189.533,\"k\":\"k\"},{\"t\":189.617,\"k\":\"j\"},{\"t\":189.733,\"k\":\"d\"},{\"t\":189.883,\"k\":\"f\"},{\"t\":190.017,\"k\":\"j\"},{\"t\":190.133,\"k\":\"d\"},{\"t\":190.233,\"k\":\"k\"},{\"t\":190.399,\"k\":\"j\"},{\"t\":190.516,\"k\":\"f\"},{\"t\":190.567,\"k\":\"k\"},{\"t\":190.767,\"k\":\"j\"},{\"t\":190.866,\"k\":\"k\"},{\"t\":190.95,\"k\":\"j\"},{\"t\":191.083,\"k\":\"f\"},{\"t\":191.233,\"k\":\"d\"},{\"t\":191.366,\"k\":\"f\"},{\"t\":191.55,\"k\":\"d\"},{\"t\":191.627,\"k\":\"f\"},{\"t\":191.777,\"k\":\"d\"},{\"t\":191.915,\"k\":\"f\"},{\"t\":192.066,\"k\":\"d\"},{\"t\":192.266,\"k\":\"f\"},{\"t\":192.383,\"k\":\"j\"},{\"t\":192.516,\"k\":\"k\"},{\"t\":192.583,\"k\":\"j\"},{\"t\":192.716,\"k\":\"k\"},{\"t\":192.816,\"k\":\"j\"},{\"t\":192.916,\"k\":\"k\"},{\"t\":192.983,\"k\":\"j\"},{\"t\":193.066,\"k\":\"k\"},{\"t\":193.15,\"k\":\"j\"},{\"t\":193.249,\"k\":\"f\"},{\"t\":193.383,\"k\":\"j\"},{\"t\":193.499,\"k\":\"f\"},{\"t\":193.616,\"k\":\"k\"},{\"t\":193.733,\"k\":\"d\"},{\"t\":193.816,\"k\":\"j\"},{\"t\":193.916,\"k\":\"f\"},{\"t\":193.999,\"k\":\"k\"},{\"t\":194.149,\"k\":\"d\"},{\"t\":194.216,\"k\":\"j\"},{\"t\":194.383,\"k\":\"fk\"},{\"t\":194.499,\"k\":\"j\"},{\"t\":194.633,\"k\":\"d\"},{\"t\":194.683,\"k\":\"k\"},{\"t\":194.799,\"k\":\"jf\"},{\"t\":194.933,\"k\":\"k\"},{\"t\":195.051,\"k\":\"d\"},{\"t\":195.093,\"k\":\"j\"},{\"t\":195.243,\"k\":\"k\"},{\"t\":195.398,\"k\":\"kj\"},{\"t\":195.465,\"k\":\"f\"},{\"t\":195.649,\"k\":\"d\"},{\"t\":195.833,\"k\":\"f\"},{\"t\":195.999,\"k\":\"f\"},{\"t\":196.183,\"k\":\"d\"},{\"t\":196.349,\"k\":\"f\"},{\"t\":196.516,\"k\":\"j\"},{\"t\":196.633,\"k\":\"f\"},{\"t\":196.749,\"k\":\"k\"},{\"t\":196.832,\"k\":\"d\"},{\"t\":196.949,\"k\":\"j\"},{\"t\":197.066,\"k\":\"f\"},{\"t\":197.17,\"k\":\"k\"},{\"t\":197.232,\"k\":\"d\"},{\"t\":197.366,\"k\":\"j\"},{\"t\":197.449,\"k\":\"f\"},{\"t\":197.632,\"k\":\"kjf\"},{\"t\":197.682,\"k\":\"d\"},{\"t\":197.866,\"k\":\"j\"},{\"t\":197.966,\"k\":\"f\"},{\"t\":198.082,\"k\":\"k\"},{\"t\":198.166,\"k\":\"d\"},{\"t\":198.299,\"k\":\"j\"},{\"t\":198.416,\"k\":\"f\"},{\"t\":198.532,\"k\":\"k\"},{\"t\":198.615,\"k\":\"d\"},{\"t\":198.732,\"k\":\"j\"},{\"t\":198.832,\"k\":\"f\"},{\"t\":198.943,\"k\":\"k\"},{\"t\":199.026,\"k\":\"d\"},{\"t\":199.143,\"k\":\"j\"},{\"t\":199.243,\"k\":\"f\"},{\"t\":199.359,\"k\":\"k\"},{\"t\":199.426,\"k\":\"d\"},{\"t\":199.509,\"k\":\"j\"},{\"t\":199.613,\"k\":\"f\"},{\"t\":199.73,\"k\":\"k\"},{\"t\":199.813,\"k\":\"d\"},{\"t\":200.032,\"k\":\"dk\"},{\"t\":200.315,\"k\":\"d\",\"h\":{\"d\":200.6652272894205}},{\"t\":200.599,\"k\":\"j\"},{\"t\":200.715,\"k\":\"f\"},{\"t\":200.799,\"k\":\"k\"},{\"t\":200.915,\"k\":\"f\",\"h\":{\"f\":201.24835606662512}},{\"t\":201.049,\"k\":\"j\"},{\"t\":201.282,\"k\":\"k\"},{\"t\":201.365,\"k\":\"f\"},{\"t\":201.465,\"k\":\"k\"},{\"t\":201.698,\"k\":\"f\"},{\"t\":201.782,\"k\":\"j\"},{\"t\":201.882,\"k\":\"f\"},{\"t\":201.982,\"k\":\"k\"},{\"t\":202.332,\"k\":\"k\"},{\"t\":202.398,\"k\":\"d\"},{\"t\":202.482,\"k\":\"j\"},{\"t\":202.648,\"k\":\"f\"},{\"t\":202.732,\"k\":\"k\"},{\"t\":202.926,\"k\":\"d\"},{\"t\":203.026,\"k\":\"k\",\"h\":{\"k\":203.38125507932747}},{\"t\":203.398,\"k\":\"f\"},{\"t\":203.465,\"k\":\"j\"},{\"t\":203.598,\"k\":\"d\"},{\"t\":203.665,\"k\":\"k\"},{\"t\":203.898,\"k\":\"d\"},{\"t\":204.015,\"k\":\"j\"},{\"t\":204.131,\"k\":\"f\"},{\"t\":204.315,\"k\":\"d\",\"h\":{\"d\":204.6976219634752}},{\"t\":204.715,\"k\":\"f\"},{\"t\":204.798,\"k\":\"j\"},{\"t\":204.915,\"k\":\"f\"},{\"t\":204.981,\"k\":\"k\"},{\"t\":205.098,\"k\":\"fj\"},{\"t\":205.331,\"k\":\"kd\"},{\"t\":205.631,\"k\":\"d\"},{\"t\":205.698,\"k\":\"j\"},{\"t\":205.831,\"k\":\"f\"},{\"t\":205.898,\"k\":\"k\"},{\"t\":206.182,\"k\":\"d\"},{\"t\":206.315,\"k\":\"j\"},{\"t\":206.381,\"k\":\"f\"},{\"t\":206.531,\"k\":\"k\"},{\"t\":206.798,\"k\":\"d\"},{\"t\":206.898,\"k\":\"j\"},{\"t\":206.981,\"k\":\"f\"},{\"t\":207.081,\"k\":\"k\"},{\"t\":207.282,\"k\":\"d\"},{\"t\":207.381,\"k\":\"j\"},{\"t\":207.464,\"k\":\"f\"},{\"t\":207.548,\"k\":\"k\"},{\"t\":207.631,\"k\":\"d\"},{\"t\":207.681,\"k\":\"j\"},{\"t\":207.781,\"k\":\"f\"},{\"t\":207.865,\"k\":\"k\"},{\"t\":207.948,\"k\":\"d\"},{\"t\":208.265,\"k\":\"d\"},{\"t\":208.448,\"k\":\"j\"},{\"t\":208.548,\"k\":\"f\"},{\"t\":208.648,\"k\":\"k\"},{\"t\":208.798,\"k\":\"d\"},{\"t\":209.064,\"k\":\"j\"},{\"t\":209.148,\"k\":\"f\"},{\"t\":209.231,\"k\":\"k\"},{\"t\":209.314,\"k\":\"d\"},{\"t\":209.398,\"k\":\"j\"},{\"t\":209.498,\"k\":\"f\"},{\"t\":209.631,\"k\":\"k\",\"h\":{\"k\":209.95822881466302}},{\"t\":209.864,\"k\":\"d\",\"h\":{\"d\":210.44769058272}},{\"t\":210.108,\"k\":\"j\"},{\"t\":210.432,\"k\":\"f\"},{\"t\":210.515,\"k\":\"k\"},{\"t\":210.765,\"k\":\"j\"},{\"t\":210.848,\"k\":\"d\"},{\"t\":210.931,\"k\":\"k\"},{\"t\":211.097,\"k\":\"f\"},{\"t\":211.147,\"k\":\"j\"},{\"t\":211.281,\"k\":\"d\"},{\"t\":211.347,\"k\":\"k\"},{\"t\":211.481,\"k\":\"j\"},{\"t\":211.531,\"k\":\"f\"},{\"t\":211.664,\"k\":\"k\"},{\"t\":211.714,\"k\":\"d\"},{\"t\":211.83,\"k\":\"j\"},{\"t\":211.897,\"k\":\"f\"},{\"t\":211.997,\"k\":\"k\"},{\"t\":212.08,\"k\":\"d\"},{\"t\":212.231,\"k\":\"fj\"},{\"t\":212.431,\"k\":\"k\"},{\"t\":212.664,\"k\":\"d\"},{\"t\":212.764,\"k\":\"j\"},{\"t\":212.847,\"k\":\"f\"},{\"t\":212.98,\"k\":\"k\"},{\"t\":213.08,\"k\":\"d\"},{\"t\":213.33,\"k\":\"j\"},{\"t\":213.431,\"k\":\"f\"},{\"t\":213.531,\"k\":\"k\"},{\"t\":213.631,\"k\":\"d\"},{\"t\":213.731,\"k\":\"j\"},{\"t\":213.848,\"k\":\"f\"},{\"t\":213.981,\"k\":\"k\"},{\"t\":214.081,\"k\":\"d\"},{\"t\":214.197,\"k\":\"k\"},{\"t\":214.364,\"k\":\"kd\"},{\"t\":214.514,\"k\":\"j\"},{\"t\":214.598,\"k\":\"f\"},{\"t\":214.681,\"k\":\"k\"},{\"t\":214.781,\"k\":\"d\"},{\"t\":214.864,\"k\":\"j\"},{\"t\":215.014,\"k\":\"fj\"},{\"t\":215.164,\"k\":\"d\"},{\"t\":215.348,\"k\":\"f\"},{\"t\":215.491,\"k\":\"j\"},{\"t\":215.607,\"k\":\"d\"},{\"t\":215.657,\"k\":\"k\"},{\"t\":215.791,\"k\":\"jf\"},{\"t\":215.948,\"k\":\"k\"},{\"t\":216.114,\"k\":\"k\"},{\"t\":216.264,\"k\":\"kd\"},{\"t\":216.448,\"k\":\"fj\"},{\"t\":216.614,\"k\":\"k\"},{\"t\":216.714,\"k\":\"d\"},{\"t\":216.764,\"k\":\"j\"},{\"t\":216.931,\"k\":\"f\"},{\"t\":217.014,\"k\":\"j\"},{\"t\":217.148,\"k\":\"d\"},{\"t\":217.23,\"k\":\"k\"},{\"t\":217.347,\"k\":\"f\"},{\"t\":217.397,\"k\":\"j\"},{\"t\":217.53,\"k\":\"dk\"},{\"t\":217.69,\"k\":\"j\"},{\"t\":217.757,\"k\":\"f\"},{\"t\":217.857,\"k\":\"k\"},{\"t\":218.096,\"k\":\"d\"},{\"t\":218.213,\"k\":\"j\"},{\"t\":218.313,\"k\":\"f\"},{\"t\":218.413,\"k\":\"k\"},{\"t\":218.547,\"k\":\"d\"},{\"t\":218.764,\"k\":\"j\"},{\"t\":218.881,\"k\":\"f\"},{\"t\":218.931,\"k\":\"k\"},{\"t\":219.064,\"k\":\"d\"},{\"t\":219.131,\"k\":\"j\"},{\"t\":219.263,\"k\":\"f\"},{\"t\":219.33,\"k\":\"k\"},{\"t\":219.447,\"k\":\"jd\"},{\"t\":219.647,\"k\":\"k\"},{\"t\":219.73,\"k\":\"jf\"},{\"t\":219.946,\"k\":\"k\"},{\"t\":220.013,\"k\":\"dj\"},{\"t\":220.18,\"k\":\"f\"},{\"t\":220.296,\"k\":\"k\"},{\"t\":220.396,\"k\":\"d\"},{\"t\":220.497,\"k\":\"k\"},{\"t\":220.547,\"k\":\"f\"},{\"t\":220.829,\"k\":\"f\"},{\"t\":221.08,\"k\":\"k\"},{\"t\":221.164,\"k\":\"j\"},{\"t\":221.214,\"k\":\"d\"},{\"t\":221.314,\"k\":\"f\"},{\"t\":221.43,\"k\":\"k\"},{\"t\":221.514,\"k\":\"j\"},{\"t\":221.58,\"k\":\"d\"},{\"t\":221.714,\"k\":\"f\"},{\"t\":221.797,\"k\":\"k\"},{\"t\":221.864,\"k\":\"j\"},{\"t\":221.993,\"k\":\"d\"},{\"t\":222.126,\"k\":\"kj\"},{\"t\":222.264,\"k\":\"f\"},{\"t\":222.447,\"k\":\"k\"},{\"t\":222.514,\"k\":\"dj\"},{\"t\":222.63,\"k\":\"f\"},{\"t\":222.79,\"k\":\"k\"},{\"t\":222.856,\"k\":\"jd\"},{\"t\":222.956,\"k\":\"f\"},{\"t\":223.157,\"k\":\"k\"},{\"t\":223.23,\"k\":\"jd\"},{\"t\":223.33,\"k\":\"f\"},{\"t\":223.513,\"k\":\"kd\"},{\"t\":223.58,\"k\":\"j\"},{\"t\":223.663,\"k\":\"f\"},{\"t\":223.813,\"k\":\"k\"},{\"t\":223.897,\"k\":\"d\"},{\"t\":224.047,\"k\":\"j\"},{\"t\":224.163,\"k\":\"f\"},{\"t\":224.296,\"k\":\"k\"},{\"t\":224.396,\"k\":\"d\"},{\"t\":224.513,\"k\":\"j\"},{\"t\":224.613,\"k\":\"f\"},{\"t\":224.713,\"k\":\"k\"},{\"t\":224.813,\"k\":\"d\"},{\"t\":224.913,\"k\":\"j\"},{\"t\":224.997,\"k\":\"f\"},{\"t\":225.113,\"k\":\"k\"},{\"t\":225.197,\"k\":\"d\"},{\"t\":225.263,\"k\":\"j\"},{\"t\":225.38,\"k\":\"f\"},{\"t\":225.446,\"k\":\"k\"},{\"t\":225.563,\"k\":\"dj\"},{\"t\":225.73,\"k\":\"f\"},{\"t\":225.83,\"k\":\"k\"},{\"t\":225.913,\"k\":\"d\"},{\"t\":226.03,\"k\":\"j\"},{\"t\":226.146,\"k\":\"f\"},{\"t\":226.262,\"k\":\"k\"},{\"t\":226.345,\"k\":\"d\"},{\"t\":226.462,\"k\":\"j\"},{\"t\":226.562,\"k\":\"f\"},{\"t\":226.679,\"k\":\"j\"},{\"t\":226.796,\"k\":\"f\"},{\"t\":226.896,\"k\":\"j\"},{\"t\":226.996,\"k\":\"f\"},{\"t\":227.096,\"k\":\"j\"},{\"t\":227.246,\"k\":\"f\"},{\"t\":227.296,\"k\":\"j\"},{\"t\":227.445,\"k\":\"f\"},{\"t\":227.495,\"k\":\"j\"},{\"t\":227.645,\"k\":\"dk\"},{\"t\":227.813,\"k\":\"k\"},{\"t\":227.996,\"k\":\"k\"},{\"t\":228.096,\"k\":\"d\"},{\"t\":228.18,\"k\":\"k\"},{\"t\":228.28,\"k\":\"d\"},{\"t\":228.363,\"k\":\"k\"},{\"t\":228.463,\"k\":\"d\"},{\"t\":228.563,\"k\":\"k\"},{\"t\":228.646,\"k\":\"d\"},{\"t\":228.779,\"k\":\"j\"},{\"t\":228.879,\"k\":\"f\"},{\"t\":228.979,\"k\":\"j\"},{\"t\":229.079,\"k\":\"f\"},{\"t\":229.179,\"k\":\"j\"},{\"t\":229.263,\"k\":\"f\"},{\"t\":229.346,\"k\":\"j\"},{\"t\":229.429,\"k\":\"f\"},{\"t\":229.513,\"k\":\"j\"},{\"t\":229.613,\"k\":\"f\"},{\"t\":229.679,\"k\":\"j\"},{\"t\":229.796,\"k\":\"fj\"},{\"t\":229.996,\"k\":\"fj\"},{\"t\":230.113,\"k\":\"fj\"},{\"t\":230.279,\"k\":\"kd\",\"h\":{\"k\":244.15468536,\"d\":244.15468536}},{\"t\":230.363,\"k\":\"j\"}]}",
  "mapId": "6w7BzSiqE5gyu291FKCuhT",
  "verified": false,
  "clonedFrom": "",
  "createdAt": 1696331275,
  "updatedAt": 1696331551
}
