{
  "id": "MaSuwnqMeYHExRlNdylL",
  "songId": "Bad-Guy-Billie-Elish-ODc5ODQwM",
  "title": "",
  "subtitle": "",
  "startAt": 14,
  "endAt": null,
  "keys": 4,
  "difficulty": 4,
  "length": 191.941,
  "noteCount": 526,
  "bpm": 0,
  "svCount": 0,
  "visualizerName": "",
  "visibility": "public",
  "isImported": false,
  "importedFrom": "",
  "importRef": "",
  "importIsOriginal": false,
  "mapping": "{\"version\":1,\"mappings\":[{\"t\":14.03,\"k\":\"dk\"},{\"t\":14.42,\"k\":\"kd\"},{\"t\":14.869,\"k\":\"fj\"},{\"t\":15.324,\"k\":\"fj\"},{\"t\":15.76,\"k\":\"kd\"},{\"t\":16.211,\"k\":\"dk\"},{\"t\":16.569,\"k\":\"f\"},{\"t\":16.744,\"k\":\"j\"},{\"t\":16.937,\"k\":\"k\"},{\"t\":17.147,\"k\":\"d\"},{\"t\":17.546,\"k\":\"f\"},{\"t\":17.602,\"k\":\"j\"},{\"t\":18.026,\"k\":\"fj\"},{\"t\":18.298,\"k\":\"d\"},{\"t\":18.494,\"k\":\"k\"},{\"t\":18.636,\"k\":\"f\"},{\"t\":19.107,\"k\":\"j\"},{\"t\":19.457,\"k\":\"d\"},{\"t\":19.933,\"k\":\"k\"},{\"t\":20.143,\"k\":\"f\"},{\"t\":20.384,\"k\":\"j\"},{\"t\":20.642,\"k\":\"d\"},{\"t\":21.093,\"k\":\"dk\"},{\"t\":21.496,\"k\":\"f\"},{\"t\":21.943,\"k\":\"d\"},{\"t\":22.073,\"k\":\"j\"},{\"t\":22.352,\"k\":\"f\"},{\"t\":22.843,\"k\":\"dk\"},{\"t\":23.276,\"k\":\"f\"},{\"t\":23.633,\"k\":\"j\"},{\"t\":23.821,\"k\":\"d\"},{\"t\":24.111,\"k\":\"k\"},{\"t\":24.644,\"k\":\"dk\"},{\"t\":25.1,\"k\":\"f\"},{\"t\":25.452,\"k\":\"d\"},{\"t\":25.652,\"k\":\"k\"},{\"t\":26.185,\"k\":\"f\"},{\"t\":26.66,\"k\":\"j\"},{\"t\":27.122,\"k\":\"d\"},{\"t\":27.344,\"k\":\"k\"},{\"t\":27.854,\"k\":\"f\"},{\"t\":28.252,\"k\":\"dk\"},{\"t\":28.668,\"k\":\"jf\"},{\"t\":29.068,\"k\":\"d\"},{\"t\":29.309,\"k\":\"f\"},{\"t\":29.799,\"k\":\"d\"},{\"t\":30.224,\"k\":\"f\"},{\"t\":30.63,\"k\":\"k\"},{\"t\":31.096,\"k\":\"j\"},{\"t\":31.355,\"k\":\"f\"},{\"t\":31.799,\"k\":\"d\"},{\"t\":32.2,\"k\":\"f\"},{\"t\":32.692,\"k\":\"d\"},{\"t\":33.117,\"k\":\"f\"},{\"t\":33.543,\"k\":\"j\"},{\"t\":33.968,\"k\":\"k\"},{\"t\":34.338,\"k\":\"d\"},{\"t\":34.67,\"k\":\"f\"},{\"t\":34.913,\"k\":\"j\"},{\"t\":35.361,\"k\":\"k\"},{\"t\":35.825,\"k\":\"f\"},{\"t\":36.276,\"k\":\"k\"},{\"t\":36.697,\"k\":\"f\"},{\"t\":37.105,\"k\":\"k\"},{\"t\":37.539,\"k\":\"f\"},{\"t\":37.969,\"k\":\"k\"},{\"t\":38.435,\"k\":\"f\"},{\"t\":38.928,\"k\":\"j\"},{\"t\":39.37,\"k\":\"d\"},{\"t\":39.843,\"k\":\"j\"},{\"t\":40.285,\"k\":\"d\"},{\"t\":40.691,\"k\":\"j\"},{\"t\":41.062,\"k\":\"d\"},{\"t\":41.602,\"k\":\"f\"},{\"t\":41.729,\"k\":\"j\"},{\"t\":41.831,\"k\":\"k\"},{\"t\":41.995,\"k\":\"d\"},{\"t\":42.517,\"k\":\"kd\"},{\"t\":42.943,\"k\":\"fj\"},{\"t\":43.395,\"k\":\"d\"},{\"t\":43.825,\"k\":\"jd\"},{\"t\":44.346,\"k\":\"d\"},{\"t\":44.719,\"k\":\"fk\"},{\"t\":45.126,\"k\":\"d\"},{\"t\":45.552,\"k\":\"dj\"},{\"t\":46.003,\"k\":\"d\"},{\"t\":46.451,\"k\":\"fk\"},{\"t\":46.882,\"k\":\"d\"},{\"t\":47.312,\"k\":\"jd\"},{\"t\":47.741,\"k\":\"d\"},{\"t\":48.206,\"k\":\"fk\"},{\"t\":48.657,\"k\":\"d\"},{\"t\":49.106,\"k\":\"dj\"},{\"t\":49.537,\"k\":\"f\"},{\"t\":50.078,\"k\":\"k\"},{\"t\":50.471,\"k\":\"d\"},{\"t\":50.949,\"k\":\"j\"},{\"t\":51.34,\"k\":\"f\"},{\"t\":51.746,\"k\":\"k\"},{\"t\":52.185,\"k\":\"d\"},{\"t\":52.683,\"k\":\"j\"},{\"t\":53.124,\"k\":\"d\"},{\"t\":53.551,\"k\":\"kd\"},{\"t\":54.024,\"k\":\"f\"},{\"t\":54.405,\"k\":\"kd\"},{\"t\":54.877,\"k\":\"f\"},{\"t\":55.187,\"k\":\"j\"},{\"t\":55.403,\"k\":\"k\"},{\"t\":56.79,\"k\":\"d\"},{\"t\":56.984,\"k\":\"f\"},{\"t\":57.222,\"k\":\"j\"},{\"t\":57.643,\"k\":\"d\"},{\"t\":57.82,\"k\":\"k\"},{\"t\":58.062,\"k\":\"k\"},{\"t\":58.272,\"k\":\"k\"},{\"t\":58.507,\"k\":\"f\"},{\"t\":58.911,\"k\":\"j\"},{\"t\":59.353,\"k\":\"d\"},{\"t\":59.575,\"k\":\"j\"},{\"t\":59.831,\"k\":\"f\"},{\"t\":60.028,\"k\":\"k\"},{\"t\":60.284,\"k\":\"d\"},{\"t\":60.667,\"k\":\"j\"},{\"t\":61.155,\"k\":\"f\"},{\"t\":61.398,\"k\":\"j\"},{\"t\":61.64,\"k\":\"k\"},{\"t\":61.896,\"k\":\"d\"},{\"t\":62.092,\"k\":\"j\"},{\"t\":62.51,\"k\":\"f\"},{\"t\":63.417,\"k\":\"d\"},{\"t\":63.635,\"k\":\"d\"},{\"t\":63.869,\"k\":\"dk\"},{\"t\":64.28,\"k\":\"f\"},{\"t\":64.546,\"k\":\"j\"},{\"t\":64.81,\"k\":\"k\"},{\"t\":65.041,\"k\":\"d\"},{\"t\":65.263,\"k\":\"j\"},{\"t\":65.564,\"k\":\"d\"},{\"t\":65.621,\"k\":\"k\"},{\"t\":66.043,\"k\":\"fj\"},{\"t\":66.501,\"k\":\"j\"},{\"t\":66.787,\"k\":\"k\"},{\"t\":66.928,\"k\":\"d\"},{\"t\":67.194,\"k\":\"j\"},{\"t\":67.36,\"k\":\"f\"},{\"t\":67.78,\"k\":\"dk\"},{\"t\":68.213,\"k\":\"f\"},{\"t\":68.455,\"k\":\"j\"},{\"t\":68.72,\"k\":\"k\"},{\"t\":68.906,\"k\":\"d\"},{\"t\":69.196,\"k\":\"fj\"},{\"t\":69.575,\"k\":\"dk\"},{\"t\":70.607,\"k\":\"f\"},{\"t\":70.896,\"k\":\"j\"},{\"t\":71.107,\"k\":\"d\",\"h\":{\"d\":72.73071308964539}},{\"t\":72.269,\"k\":\"j\"},{\"t\":74.214,\"k\":\"f\"},{\"t\":74.574,\"k\":\"k\"},{\"t\":74.783,\"k\":\"d\"},{\"t\":75.211,\"k\":\"j\"},{\"t\":75.377,\"k\":\"f\"},{\"t\":75.596,\"k\":\"k\"},{\"t\":75.829,\"k\":\"d\"},{\"t\":76.026,\"k\":\"j\"},{\"t\":76.267,\"k\":\"k\"},{\"t\":76.476,\"k\":\"f\"},{\"t\":76.905,\"k\":\"k\"},{\"t\":77.07,\"k\":\"f\"},{\"t\":77.266,\"k\":\"j\"},{\"t\":77.478,\"k\":\"d\"},{\"t\":77.629,\"k\":\"k\"},{\"t\":77.84,\"k\":\"f\"},{\"t\":78.012,\"k\":\"j\"},{\"t\":78.268,\"k\":\"d\"},{\"t\":78.721,\"k\":\"j\"},{\"t\":78.907,\"k\":\"d\"},{\"t\":79.085,\"k\":\"j\"},{\"t\":79.319,\"k\":\"f\"},{\"t\":79.498,\"k\":\"k\"},{\"t\":79.704,\"k\":\"d\"},{\"t\":79.876,\"k\":\"j\"},{\"t\":80.088,\"k\":\"f\"},{\"t\":80.498,\"k\":\"k\"},{\"t\":80.705,\"k\":\"d\"},{\"t\":80.878,\"k\":\"j\"},{\"t\":81.067,\"k\":\"f\"},{\"t\":81.241,\"k\":\"k\"},{\"t\":81.407,\"k\":\"d\"},{\"t\":81.646,\"k\":\"d\"},{\"t\":81.84,\"k\":\"j\"},{\"t\":82.259,\"k\":\"f\"},{\"t\":82.481,\"k\":\"k\"},{\"t\":82.644,\"k\":\"d\"},{\"t\":82.863,\"k\":\"j\"},{\"t\":83.053,\"k\":\"f\"},{\"t\":83.25,\"k\":\"f\"},{\"t\":83.398,\"k\":\"k\"},{\"t\":83.654,\"k\":\"f\"},{\"t\":84.104,\"k\":\"j\"},{\"t\":84.251,\"k\":\"d\"},{\"t\":84.49,\"k\":\"j\"},{\"t\":84.725,\"k\":\"f\"},{\"t\":84.877,\"k\":\"k\"},{\"t\":85.131,\"k\":\"d\"},{\"t\":85.398,\"k\":\"j\"},{\"t\":85.818,\"k\":\"f\"},{\"t\":86.037,\"k\":\"j\"},{\"t\":86.248,\"k\":\"d\"},{\"t\":86.677,\"k\":\"k\"},{\"t\":87.232,\"k\":\"f\"},{\"t\":87.845,\"k\":\"j\"},{\"t\":88.262,\"k\":\"d\"},{\"t\":88.711,\"k\":\"d\"},{\"t\":89.16,\"k\":\"j\",\"h\":{\"j\":89.53207904196167}},{\"t\":89.855,\"k\":\"f\"},{\"t\":90.307,\"k\":\"k\"},{\"t\":90.724,\"k\":\"d\"},{\"t\":91.194,\"k\":\"f\"},{\"t\":91.644,\"k\":\"j\"},{\"t\":91.831,\"k\":\"d\",\"h\":{\"d\":92.20455182833862}},{\"t\":92.33,\"k\":\"k\"},{\"t\":92.726,\"k\":\"f\"},{\"t\":93.429,\"k\":\"j\"},{\"t\":93.869,\"k\":\"d\"},{\"t\":94.252,\"k\":\"k\"},{\"t\":94.695,\"k\":\"f\"},{\"t\":95.121,\"k\":\"j\"},{\"t\":95.361,\"k\":\"k\",\"h\":{\"k\":95.71061587030029}},{\"t\":95.917,\"k\":\"f\"},{\"t\":96.275,\"k\":\"j\"},{\"t\":96.947,\"k\":\"d\"},{\"t\":97.4,\"k\":\"j\"},{\"t\":97.841,\"k\":\"f\"},{\"t\":98.246,\"k\":\"k\"},{\"t\":98.71,\"k\":\"f\"},{\"t\":98.923,\"k\":\"d\",\"h\":{\"d\":99.31877398283386}},{\"t\":99.443,\"k\":\"j\"},{\"t\":99.841,\"k\":\"f\"},{\"t\":100.499,\"k\":\"k\"},{\"t\":100.916,\"k\":\"d\"},{\"t\":101.438,\"k\":\"j\"},{\"t\":101.626,\"k\":\"f\"},{\"t\":101.982,\"k\":\"j\"},{\"t\":102.105,\"k\":\"f\"},{\"t\":102.233,\"k\":\"k\"},{\"t\":102.417,\"k\":\"d\"},{\"t\":102.708,\"k\":\"j\"},{\"t\":102.967,\"k\":\"f\"},{\"t\":103.395,\"k\":\"k\"},{\"t\":103.811,\"k\":\"d\"},{\"t\":104.285,\"k\":\"j\"},{\"t\":104.703,\"k\":\"d\"},{\"t\":105.131,\"k\":\"j\"},{\"t\":105.572,\"k\":\"d\"},{\"t\":106.026,\"k\":\"j\"},{\"t\":106.495,\"k\":\"k\"},{\"t\":106.913,\"k\":\"f\"},{\"t\":107.387,\"k\":\"k\"},{\"t\":107.805,\"k\":\"f\"},{\"t\":108.256,\"k\":\"k\"},{\"t\":108.696,\"k\":\"f\"},{\"t\":109.128,\"k\":\"k\"},{\"t\":109.566,\"k\":\"f\"},{\"t\":110.035,\"k\":\"d\"},{\"t\":110.508,\"k\":\"j\"},{\"t\":110.95,\"k\":\"d\"},{\"t\":111.401,\"k\":\"j\"},{\"t\":111.821,\"k\":\"d\"},{\"t\":112.247,\"k\":\"j\"},{\"t\":112.688,\"k\":\"d\"},{\"t\":113.139,\"k\":\"j\"},{\"t\":113.603,\"k\":\"f\"},{\"t\":114.057,\"k\":\"k\"},{\"t\":114.52,\"k\":\"f\"},{\"t\":114.97,\"k\":\"k\"},{\"t\":115.388,\"k\":\"f\"},{\"t\":115.888,\"k\":\"k\"},{\"t\":116.602,\"k\":\"d\"},{\"t\":116.822,\"k\":\"j\"},{\"t\":116.989,\"k\":\"f\"},{\"t\":117.21,\"k\":\"kd\"},{\"t\":117.589,\"k\":\"fj\"},{\"t\":118.05,\"k\":\"k\"},{\"t\":118.28,\"k\":\"d\"},{\"t\":118.544,\"k\":\"f\"},{\"t\":118.761,\"k\":\"j\"},{\"t\":118.934,\"k\":\"kd\"},{\"t\":119.338,\"k\":\"fj\"},{\"t\":119.797,\"k\":\"k\"},{\"t\":120.058,\"k\":\"j\"},{\"t\":120.292,\"k\":\"f\"},{\"t\":120.484,\"k\":\"d\"},{\"t\":120.68,\"k\":\"dk\"},{\"t\":121.09,\"k\":\"jf\"},{\"t\":121.52,\"k\":\"j\"},{\"t\":121.778,\"k\":\"f\"},{\"t\":122.045,\"k\":\"k\"},{\"t\":122.255,\"k\":\"d\"},{\"t\":122.493,\"k\":\"fj\"},{\"t\":122.9,\"k\":\"dk\"},{\"t\":123.867,\"k\":\"j\"},{\"t\":124.087,\"k\":\"j\"},{\"t\":124.293,\"k\":\"dk\"},{\"t\":124.725,\"k\":\"f\"},{\"t\":125.175,\"k\":\"j\"},{\"t\":125.369,\"k\":\"k\"},{\"t\":125.625,\"k\":\"d\"},{\"t\":125.887,\"k\":\"f\"},{\"t\":126.078,\"k\":\"dk\"},{\"t\":126.466,\"k\":\"f\"},{\"t\":126.917,\"k\":\"j\"},{\"t\":127.178,\"k\":\"k\"},{\"t\":127.412,\"k\":\"d\"},{\"t\":127.608,\"k\":\"j\"},{\"t\":127.842,\"k\":\"dk\"},{\"t\":128.184,\"k\":\"f\"},{\"t\":128.701,\"k\":\"j\"},{\"t\":128.91,\"k\":\"d\"},{\"t\":129.18,\"k\":\"k\"},{\"t\":129.413,\"k\":\"f\"},{\"t\":129.604,\"k\":\"d\"},{\"t\":130.056,\"k\":\"j\"},{\"t\":131.074,\"k\":\"d\"},{\"t\":131.244,\"k\":\"f\"},{\"t\":131.633,\"k\":\"j\",\"h\":{\"j\":133.1759739370575}},{\"t\":132.642,\"k\":\"d\"},{\"t\":134.492,\"k\":\"dk\"},{\"t\":134.996,\"k\":\"f\"},{\"t\":135.216,\"k\":\"j\"},{\"t\":135.634,\"k\":\"d\"},{\"t\":135.833,\"k\":\"j\"},{\"t\":136.044,\"k\":\"f\"},{\"t\":136.264,\"k\":\"k\"},{\"t\":136.473,\"k\":\"d\"},{\"t\":136.671,\"k\":\"j\"},{\"t\":136.858,\"k\":\"d\"},{\"t\":137.356,\"k\":\"k\"},{\"t\":137.567,\"k\":\"f\"},{\"t\":137.811,\"k\":\"j\"},{\"t\":138.043,\"k\":\"d\"},{\"t\":138.244,\"k\":\"k\"},{\"t\":138.476,\"k\":\"f\"},{\"t\":138.65,\"k\":\"j\"},{\"t\":139.182,\"k\":\"d\"},{\"t\":139.358,\"k\":\"k\"},{\"t\":139.592,\"k\":\"f\"},{\"t\":139.788,\"k\":\"j\"},{\"t\":139.998,\"k\":\"d\"},{\"t\":140.221,\"k\":\"k\"},{\"t\":140.431,\"k\":\"f\"},{\"t\":140.927,\"k\":\"j\"},{\"t\":141.16,\"k\":\"d\"},{\"t\":141.383,\"k\":\"k\"},{\"t\":141.57,\"k\":\"f\"},{\"t\":141.743,\"k\":\"j\"},{\"t\":141.999,\"k\":\"d\"},{\"t\":142.244,\"k\":\"j\"},{\"t\":142.76,\"k\":\"k\"},{\"t\":142.956,\"k\":\"k\"},{\"t\":143.14,\"k\":\"f\"},{\"t\":143.383,\"k\":\"j\"},{\"t\":143.593,\"k\":\"d\"},{\"t\":143.794,\"k\":\"k\"},{\"t\":144.002,\"k\":\"f\"},{\"t\":144.476,\"k\":\"j\"},{\"t\":144.663,\"k\":\"d\"},{\"t\":144.93,\"k\":\"j\"},{\"t\":145.141,\"k\":\"f\"},{\"t\":145.317,\"k\":\"k\"},{\"t\":145.502,\"k\":\"d\"},{\"t\":145.816,\"k\":\"j\"},{\"t\":146.234,\"k\":\"f\"},{\"t\":146.478,\"k\":\"j\"},{\"t\":146.688,\"k\":\"d\"},{\"t\":147.117,\"k\":\"k\"},{\"t\":147.627,\"k\":\"f\"},{\"t\":148.765,\"k\":\"d\"},{\"t\":149.12,\"k\":\"dk\"},{\"t\":149.572,\"k\":\"fj\"},{\"t\":150.119,\"k\":\"d\"},{\"t\":150.315,\"k\":\"j\"},{\"t\":150.526,\"k\":\"f\"},{\"t\":150.7,\"k\":\"j\"},{\"t\":150.933,\"k\":\"dk\"},{\"t\":151.3,\"k\":\"jf\"},{\"t\":151.663,\"k\":\"j\"},{\"t\":151.856,\"k\":\"k\"},{\"t\":152.089,\"k\":\"f\"},{\"t\":152.263,\"k\":\"j\"},{\"t\":152.473,\"k\":\"d\"},{\"t\":152.671,\"k\":\"kd\"},{\"t\":153.029,\"k\":\"fj\"},{\"t\":153.466,\"k\":\"k\"},{\"t\":153.629,\"k\":\"d\"},{\"t\":153.85,\"k\":\"j\"},{\"t\":154.018,\"k\":\"f\"},{\"t\":154.235,\"k\":\"k\"},{\"t\":154.468,\"k\":\"dk\"},{\"t\":154.859,\"k\":\"jf\"},{\"t\":155.383,\"k\":\"k\"},{\"t\":155.569,\"k\":\"d\"},{\"t\":155.767,\"k\":\"j\"},{\"t\":156.002,\"k\":\"f\"},{\"t\":156.238,\"k\":\"dk\"},{\"t\":156.672,\"k\":\"fj\"},{\"t\":157.086,\"k\":\"k\"},{\"t\":157.295,\"k\":\"d\"},{\"t\":157.516,\"k\":\"j\"},{\"t\":157.704,\"k\":\"f\"},{\"t\":157.895,\"k\":\"d\"},{\"t\":158.05,\"k\":\"kd\"},{\"t\":158.428,\"k\":\"fj\"},{\"t\":158.891,\"k\":\"j\"},{\"t\":159.052,\"k\":\"f\"},{\"t\":159.272,\"k\":\"k\"},{\"t\":159.459,\"k\":\"d\"},{\"t\":159.794,\"k\":\"dk\"},{\"t\":160.201,\"k\":\"fj\"},{\"t\":160.659,\"k\":\"k\"},{\"t\":160.891,\"k\":\"d\"},{\"t\":161.136,\"k\":\"j\"},{\"t\":161.324,\"k\":\"f\"},{\"t\":161.543,\"k\":\"j\"},{\"t\":162.031,\"k\":\"f\"},{\"t\":162.476,\"k\":\"d\"},{\"t\":162.925,\"k\":\"f\"},{\"t\":165.367,\"k\":\"dk\"},{\"t\":165.513,\"k\":\"fj\"},{\"t\":165.666,\"k\":\"dk\"},{\"t\":166.351,\"k\":\"fj\"},{\"t\":166.76,\"k\":\"dk\"},{\"t\":166.985,\"k\":\"fj\"},{\"t\":167.183,\"k\":\"dk\"},{\"t\":168.099,\"k\":\"fj\"},{\"t\":169.118,\"k\":\"d\"},{\"t\":169.174,\"k\":\"k\"},{\"t\":169.41,\"k\":\"fj\"},{\"t\":169.632,\"k\":\"dk\"},{\"t\":170.116,\"k\":\"j\"},{\"t\":170.678,\"k\":\"kd\"},{\"t\":170.897,\"k\":\"fj\"},{\"t\":171.103,\"k\":\"kd\"},{\"t\":172.082,\"k\":\"f\"},{\"t\":173.149,\"k\":\"d\"},{\"t\":173.694,\"k\":\"j\"},{\"t\":173.905,\"k\":\"f\"},{\"t\":174.218,\"k\":\"k\"},{\"t\":174.449,\"k\":\"d\"},{\"t\":174.671,\"k\":\"j\"},{\"t\":177.142,\"k\":\"d\",\"h\":{\"d\":177.6063490896454}},{\"t\":177.894,\"k\":\"j\"},{\"t\":178.242,\"k\":\"f\"},{\"t\":178.717,\"k\":\"k\",\"h\":{\"k\":179.11079003814697}},{\"t\":179.387,\"k\":\"f\"},{\"t\":179.676,\"k\":\"j\"},{\"t\":180.162,\"k\":\"d\"},{\"t\":181.19,\"k\":\"k\"},{\"t\":181.722,\"k\":\"f\"},{\"t\":182.01,\"k\":\"j\"},{\"t\":182.221,\"k\":\"d\"},{\"t\":182.787,\"k\":\"k\",\"h\":{\"k\":183.2506310705719}},{\"t\":183.412,\"k\":\"f\"},{\"t\":183.655,\"k\":\"j\"},{\"t\":184.194,\"k\":\"k\"},{\"t\":185.207,\"k\":\"d\"},{\"t\":185.378,\"k\":\"f\"},{\"t\":185.551,\"k\":\"j\"},{\"t\":185.791,\"k\":\"k\"},{\"t\":185.931,\"k\":\"d\"},{\"t\":186.221,\"k\":\"j\"},{\"t\":186.363,\"k\":\"f\"},{\"t\":186.608,\"k\":\"k\"},{\"t\":186.747,\"k\":\"d\"},{\"t\":187.083,\"k\":\"j\"},{\"t\":187.226,\"k\":\"f\"},{\"t\":187.423,\"k\":\"k\"},{\"t\":187.563,\"k\":\"d\"},{\"t\":187.761,\"k\":\"j\"},{\"t\":187.927,\"k\":\"f\"},{\"t\":188.195,\"k\":\"kd\"},{\"t\":188.762,\"k\":\"jf\"},{\"t\":189.258,\"k\":\"d\"},{\"t\":189.753,\"k\":\"j\"},{\"t\":189.993,\"k\":\"k\"},{\"t\":190.226,\"k\":\"f\"},{\"t\":190.747,\"k\":\"j\"},{\"t\":191.28,\"k\":\"f\"},{\"t\":191.663,\"k\":\"k\"},{\"t\":191.94,\"k\":\"d\"},{\"t\":192.208,\"k\":\"j\"},{\"t\":192.673,\"k\":\"f\"},{\"t\":193.148,\"k\":\"k\"},{\"t\":193.408,\"k\":\"j\"},{\"t\":193.666,\"k\":\"f\"},{\"t\":193.973,\"k\":\"d\"},{\"t\":194.195,\"k\":\"k\"},{\"t\":194.681,\"k\":\"f\"},{\"t\":195.154,\"k\":\"j\"},{\"t\":195.642,\"k\":\"f\"},{\"t\":195.933,\"k\":\"k\"},{\"t\":196.095,\"k\":\"d\"},{\"t\":196.705,\"k\":\"f\"},{\"t\":197.178,\"k\":\"k\"},{\"t\":197.459,\"k\":\"d\"},{\"t\":197.699,\"k\":\"j\"},{\"t\":197.912,\"k\":\"f\"},{\"t\":198.202,\"k\":\"k\"},{\"t\":198.664,\"k\":\"d\"},{\"t\":199.185,\"k\":\"j\"},{\"t\":199.442,\"k\":\"f\"},{\"t\":199.663,\"k\":\"k\"},{\"t\":199.941,\"k\":\"d\"},{\"t\":200.186,\"k\":\"j\"},{\"t\":200.674,\"k\":\"f\"},{\"t\":201.188,\"k\":\"d\"},{\"t\":201.427,\"k\":\"f\"},{\"t\":201.717,\"k\":\"j\"},{\"t\":201.957,\"k\":\"k\"},{\"t\":202.167,\"k\":\"f\"},{\"t\":202.687,\"k\":\"j\"},{\"t\":203.149,\"k\":\"d\"},{\"t\":203.374,\"k\":\"k\"},{\"t\":203.629,\"k\":\"f\"},{\"t\":203.825,\"k\":\"j\"},{\"t\":204.127,\"k\":\"d\"},{\"t\":204.67,\"k\":\"k\"}]}",
  "mapId": "Gfy3F5sqQgXMKeVWGWBw",
  "verified": false,
  "clonedFrom": "",
  "createdAt": 1593340435,
  "updatedAt": 1600774818
}
