[
  {
    "id": "DqKzr61G1Kz5pYpJJmuVmW",
    "songId": "PFvFqrQi4dZePm3dZGkTy",
    "title": "",
    "subtitle": "",
    "startAt": 0,
    "endAt": 0,
    "keys": 4,
    "difficulty": 8,
    "length": 208.929,
    "noteCount": 1061,
    "bpm": 0,
    "svCount": 0,
    "visualizerName": "",
    "visibility": "public",
    "isImported": false,
    "importedFrom": "",
    "importRef": "",
    "importIsOriginal": false,
    "mapping": "",
    "mapId": "CHDpsiP9TzE2D5KkbxYDs4",
    "verified": false,
    "clonedFrom": "",
    "createdAt": 1727551120,
    "updatedAt": 1727552657
  },
  {
    "id": "EUXEdzXGSeST8qhdLCFerY",
    "songId": "PFvFqrQi4dZePm3dZGkTy",
    "title": "",
    "subtitle": "",
    "startAt": 0,
    "endAt": 0,
    "keys": 4,
    "difficulty": 10,
    "length": 240.521,
    "noteCount": 1277,
    "bpm": 0,
    "svCount": 0,
    "visualizerName": "",
    "visibility": "public",
    "isImported": false,
    "importedFrom": "",
    "importRef": "",
    "importIsOriginal": false,
    "mapping": "",
    "mapId": "KLXCCE6BPTThSEtghvgDNx",
    "verified": false,
    "clonedFrom": "",
    "createdAt": 1727550720,
    "updatedAt": 1727552630
  },
  {
    "id": "Pe3WdqvhjbUVN83uctxxZB",
    "songId": "PFvFqrQi4dZePm3dZGkTy",
    "title": "the chart that sounds like the song",
    "subtitle": "",
    "startAt": 0,
    "endAt": 0,
    "keys": 4,
    "difficulty": 6,
    "length": 205.715,
    "noteCount": 540,
    "bpm": 0,
    "svCount": 0,
    "visualizerName": "",
    "visibility": "public",
    "isImported": false,
    "importedFrom": "",
    "importRef": "",
    "importIsOriginal": false,
    "mapping": "",
    "mapId": "LJyC1FspiKEdRe1HbdkbZz",
    "verified": false,
    "clonedFrom": "",
    "createdAt": 1727731978,
    "updatedAt": 1727732436
  }
]
